Workbook
Name IQ_CH: 110000
Name IQ_CQ: 5000
Name IQ_CY: 10000
Name IQ_DAILY: 500000
Name IQ_FH: 100000
Name IQ_FQ: 500
Name IQ_FY: 1000
Name IQ_LTM: 2000
Name IQ_MONTH: 15000
Name IQ_NTM: 6000
Name IQ_WEEK: 50000
Name IQ_YTD: 3000

Sheet DCF
B1: PepsiCo DCF Valuation
B2: ='PepsiCo-IS'!A2 -> (in USD million except per Share Data)
B3: Valuation Date | C3: 44104
B5: Choose Discounting | E5: 2
AF6: Mid Year Discounting
C7: ='PepsiCo-IS'!I3 -> 6 | D7: ='PepsiCo-IS'!K3 -> 12 | E7: ='PepsiCo-IS'!L3 -> 12 | F7: ='PepsiCo-IS'!M3 -> 12 | G7: ='PepsiCo-IS'!N3 -> 12 | AF7: Year End Discounting
B8: Date of cash flows | C8: ='PepsiCo-IS'!I4 -> 44196 | D8: ='PepsiCo-IS'!K4 -> 44561 | E8: ='PepsiCo-IS'!L4 -> 44926 | F8: ='PepsiCo-IS'!M4 -> 45291 | G8: ='PepsiCo-IS'!N4 -> 45657
B10: EBIT | C10: ='PepsiCo-IS'!I22 -> 6280.1228 | D10: ='PepsiCo-IS'!K22 -> 11541.677 | E10: ='PepsiCo-IS'!L22 -> 12019.53 | F10: ='PepsiCo-IS'!M22 -> 12523.531 | G10: ='PepsiCo-IS'!N22 -> 13055.351
B11: Tax Rate | C11: ='PepsiCo-IS'!I68 -> 0.21485287 | D11: ='PepsiCo-IS'!K68 -> 0.22619544 | E11: ='PepsiCo-IS'!L68 -> 0.24079696 | F11: ='PepsiCo-IS'!M68 -> 0.25539848 | G11: ='PepsiCo-IS'!N68 -> 0.27 | H11: 0.27
B12: Tax expense | C12: =-C10*C11 -> -1349.3024 | D12: =-D10*D11 -> -2610.6748 | E12: =-E10*E11 -> -2894.2663 | F12: =-F10*F11 -> -3198.4909 | G12: =-G10*G11 -> -3524.9447
B13: NOPAT | C13: =C12+C10 -> 4930.8204 | D13: =D12+D10 -> 8931.0025 | E13: =E12+E10 -> 9125.2637 | F13: =F12+F10 -> 9325.0404 | G13: =G12+G10 -> 9530.4062
B14: Add: Depreciation and amortisation | C14: ='PepsiCo-CFS'!B8 -> 1267.4709 | D14: ='PepsiCo-CFS'!C8 -> 2632.5475 | E14: ='PepsiCo-CFS'!D8 -> 2733.997 | F14: ='PepsiCo-CFS'!E8 -> 2841.4158 | G14: ='PepsiCo-CFS'!F8 -> 2955.1632 | I14: All from CFS
B15: Add/Less: (Increase)/ Decrease in net working capital | C15: =SUM('PepsiCo-CFS'!B11:B14) -> 2918.1112 | D15: =SUM('PepsiCo-CFS'!C11:C14) -> 374.66333 | E15: =SUM('PepsiCo-CFS'!D11:D14) -> 146.34667 | F15: =SUM('PepsiCo-CFS'!E11:E14) -> 154.46044 | G15: =SUM('PepsiCo-CFS'!F11:F14) -> 163.08688
B16: Less: Capital expenditure | C16: ='PepsiCo-CFS'!B19 -> -2348.5197 | D16: ='PepsiCo-CFS'!C19 -> -2100.0133 | E16: ='PepsiCo-CFS'!D19 -> -3479.2286 | F16: ='PepsiCo-CFS'!E19 -> -3634.7676 | G16: ='PepsiCo-CFS'!F19 -> -3799.3231
B17: Debt free cash flow (Free Cash Flows to Firm) | C17: =SUM(C13:C16) -> 6767.8828 | D17: =SUM(D13:D16) -> 9838.2 | E17: =SUM(E13:E16) -> 8526.3788 | F17: =SUM(F13:F16) -> 8686.149 | G17: =SUM(G13:G16) -> 8849.3331 | H17: =G17*(1+D29) -> 9027.2047
A18: =WACC!N8 -> 0.052190726 | B18: Discount rate (%)
B19: Full Period or Partial Period | C19: =_xlfn.DAYS(C8,$C$3)/30/C7 -> 0.51111111 | D19: 1 | E19: 1 | F19: 1 | G19: 1
B20: Discounting Period-Year End | C20: =_xlfn.DAYS(C8,$C$3)/30/12 -> 0.25555556 | D20: =_xlfn.DAYS(D8,$C$3)/30/12 -> 1.2694444 | E20: =_xlfn.DAYS(E8,$C$3)/30/12 -> 2.2833333 | F20: =_xlfn.DAYS(F8,$C$3)/30/12 -> 3.2972222 | G20: =_xlfn.DAYS(G8,$C$3)/30/12 -> 4.3138889 | I20: Assumed CF is coming at end of period | M20: 2
B21: Discounting Period-Mid Year | C21: =C20/2 -> 0.12777778 | D21: =D20-0.5 -> 0.76944444 | E21: =E20-0.5 -> 1.7833333 | F21: =F20-0.5 -> 2.7972222 | G21: =G20-0.5 -> 3.8138889 | I21: Assumed CF is coming at middle of period | M21: 1
B22: Present value factor- END year discounting | C22: =(1+$A$18)^C20 -> 1.0130861 | D22: =(1+$A$18)^D20 -> 1.0667133 | E22: =(1+$A$18)^E20 -> 1.1231792 | F22: =(1+$A$18)^F20 -> 1.182634 | G22: =(1+$A$18)^G20 -> 1.2454121 | I22: Denominator
B23: Present value factor- MID year discounting | C23: =(1+$A$18)^C21 -> 1.0065218 | D23: =(1+$A$18)^D21 -> 1.0399213 | E23: =(1+$A$18)^E21 -> 1.094969 | F23: =(1+$A$18)^F21 -> 1.1529305 | G23: =(1+$A$18)^G21 -> 1.2141319
B24: Present value debt free cash flow | C24: =IF($E$5=2,C17*C19/C22,C17/C23) -> 3414.4581 | D24: =IF($E$5=2,D17*D19/D22,D17/D23) -> 9222.9095 | E24: =IF($E$5=2,E17*E19/E22,E17/E23) -> 7591.29 | F24: =IF($E$5=2,F17*F19/F22,F17/F23) -> 7344.7479 | G24: =IF($E$5=2,G17*G19/G22,G17/G23) -> 7105.546
B26: Present value for explicit period (4.5 Years) | G26: =SUM(C24:G24) -> 34678.952
J27: WACC
B28: Terminal value (for after 4.5 years) | D28: Gordon growth | I28: =D40 -> 164.16919 | J28: 0.045 | K28: =J28+0.25% -> 0.0475 | L28: =K28+0.25% -> 0.05 | M28: =L28+0.25% -> 0.0525 | N28: =M28+0.25% -> 0.055 | O28: =N28+0.25% -> 0.0575 | P28: =O28+0.25% -> 0.06 | Q28: =P28+0.25% -> 0.0625 | R28: =Q28+0.25% -> 0.065
B29: Long Term Growth Rate | D29: 0.0201 | E29: Close to US GDP Growth rate | H29: LTGR | I29: 0.01 | J29: 153.99954 | K29: 142.22178 | L29: 131.91634 | M29: 122.8234 | N29: 114.74086 | O29: 107.5092 | P29: 101.00077 | Q29: 95.112264 | R29: 89.759136
B30: Terminal Value | D30: =H17/(A18-D29) -> 281302.6 | E30: Discount sitting at 4.5 years | I30: =I29+0.25% -> 0.0125 | J30: 166.13945 | K30: 152.66005 | L30: 140.97796 | M30: 130.75618 | N30: 121.737 | O30: 113.72 | P30: 106.54692 | Q30: 100.09119 | R30: 94.250315
B31: Present Value of TV | D31: =D30/CHOOSE(E5,G23,G22) -> 225871.09 | E31: Present Value of Remaining period | I31: =I30+0.25% -> 0.015 | J31: 180.30267 | K31: 164.7042 | L31: 151.33409 | M31: 139.74666 | N31: 129.60766 | O31: 120.66147 | P31: 112.70931 | Q31: 105.59421 | R31: 99.190612
B32: DCF Value of Firm / Operating Business Enterprise Value | D32: =D31+G26 -> 260550.05 | E32: Operating worth only | I32: =I31+0.25% -> 0.0175 | J32: 197.04102 | K32: 178.75572 | L32: 163.28348 | M32: 150.0215 | N32: 138.52773 | O32: 128.47064 | P32: 119.59668 | Q32: 111.70868 | R32: 104.65094
B33: Add: Non Operating Assets | D33: ='PepsiCo-BS'!E17+'PepsiCo-BS'!E6 -> 2911 | I33: =I32+0.25% -> 0.02 | J33: 217.12704 | K33: 195.36205 | L33: 177.22442 | M33: 161.87708 | N33: 148.72211 | O33: 137.32102 | P33: 127.34498 | Q33: 118.54249 | R33: 110.71797
B34: Total Value of Firm | D34: =SUM(D32:D33) -> 263461.05 | I34: =I33+0.25% -> 0.0225 | J34: 241.67663 | K34: 215.28965 | L34: 193.70009 | M34: 175.7086 | N34: 160.48485 | O34: 147.43575 | P34: 136.12638 | Q34: 126.23054 | R34: 117.49877
B35: Less: Gross Debt & Debt Equivalents | D35: ='PepsiCo-BS'!E23+'PepsiCo-BS'!E27 -> 44978 | I35: =I34+0.25% -> 0.025 | J35: 272.36361 | K35: 239.6456 | L35: 213.47089 | M35: 192.05493 | N35: 174.20804 | O35: 159.10659 | P35: 146.16227 | Q35: 134.94365 | R35: 125.12717
B36: Add: Cash | D36: ='PepsiCo-BS'!E5 -> 8927 | I36: =I35+0.25% -> 0.0275 | J36: 311.81829 | K36: 270.09055 | L36: 237.6352 | M36: 211.67053 | N36: 190.42636 | O36: 172.72257 | P36: 157.74214 | Q36: 144.9015 | R36: 133.77269
B37: Less: Non Controling Interest | D37: ='PepsiCo-BS'!E41 -> 96 | I37: =I36+0.25% -> 0.03 | J37: 364.42454 | K37: 309.23405 | L37: 267.84059 | M37: 235.64516 | N37: 209.88835 | O37: 188.81418 | P37: 171.25199 | Q37: 156.39132 | R37: 143.65328
B38: DCF value of Common Equity | D38: =D34-D35+D36-D37 -> 227314.05
B39: No. of shares o/s-Diluted | D39: =1384632842/1000000 -> 1384.6328 | E39: Not Weigthed average. Exact Shares on that day
B40: DCF value per share | D40: =D38/D39 -> 164.16919
J41: WACC
B42: Terminal Value | D42: Exit Multiple Method | I42: =D55 -> 131.02483 | J42: =J28 -> 0.045 | K42: =K28 -> 0.0475 | L42: =L28 -> 0.05 | M42: =M28 -> 0.0525 | N42: =N28 -> 0.055 | O42: =O28 -> 0.0575 | P42: =P28 -> 0.06 | Q42: =Q28 -> 0.0625 | R42: =R28 -> 0.065
B43: LTM EV/EBITDA | D43: 14 | E43: Time Sensitive multiple | H43: Exit Multiple | I43: 11 | J43: 106.66223 | K43: 105.4345 | L43: 104.22183 | M43: 103.02401 | N43: 101.8408 | O43: 100.67201 | P43: 99.517414 | Q43: 98.376809 | R43: 97.249991
B44: Terminal Year EBITDA | D44: =G10+G14 -> 16010.514 | E44: PROJECTED EBITDA of AFTER 4.5 years | I44: =I43+1 -> 12 | J44: 116.22547 | K44: 114.89967 | L44: 113.59017 | M44: 112.29672 | N44: 111.0191 | O44: 109.75707 | P44: 108.5104 | Q44: 107.27887 | R44: 106.06225
B45: Terminal Value | D45: =D44*D43 -> 224147.2 | I45: =I44+1 -> 13 | J45: 125.78872 | K45: 124.36484 | L45: 122.9585 | M45: 121.56944 | N45: 120.1974 | O45: 118.84213 | P45: 117.50339 | Q45: 116.18093 | R45: 114.87452
B46: Present Value of TV | D46: =D45/CHOOSE(E5,G23,G22) -> 179978.33 | E46: Terminal Discounted | I46: =I45+1 -> 14 | J46: 135.35196 | K46: 133.83001 | L46: 132.32684 | M46: 130.84216 | N46: 129.3757 | O46: 127.92719 | P46: 126.49637 | Q46: 125.08299 | R46: 123.68678
B47: DCF Value of Firm / Operating Business Enterprise Value | D47: =D46+G26 -> 214657.28 | E47: Terminal Discounted + Projected years | I47: =I46+1 -> 15 | J47: 144.9152 | K47: 143.29518 | L47: 141.69517 | M47: 140.11487 | N47: 138.55399 | O47: 137.01225 | P47: 135.48936 | Q47: 133.98505 | R47: 132.49905
B48: Add: Non Operating Assets | D48: =D33 -> 2911 | I48: =I47+1 -> 16 | J48: 154.47844 | K48: 152.76035 | L48: 151.0635 | M48: 149.38759 | N48: 147.73229 | O48: 146.09731 | P48: 144.48235 | Q48: 142.88711 | R48: 141.31131
B49: Total Value of Firm | D49: =SUM(D47:D48) -> 217568.28 | I49: =I48+1 -> 17 | J49: 164.04168 | K49: 162.22552 | L49: 160.43184 | M49: 158.6603 | N49: 156.91059 | O49: 155.18237 | P49: 153.47534 | Q49: 151.78917 | R49: 150.12357
B50: Less: Gross Debt & Debt Equivalents | D50: =D35 -> 44978 | I50: =I49+1 -> 18 | J50: 173.60492 | K50: 171.69069 | L50: 169.80017 | M50: 167.93302 | N50: 166.08889 | O50: 164.26743 | P50: 162.46832 | Q50: 160.69123 | R50: 158.93584
B51: Add: Cash | D51: =D36 -> 8927 | I51: =I50+1 -> 19 | J51: 183.16816 | K51: 181.15586 | L51: 179.16851 | M51: 177.20574 | N51: 175.26718 | O51: 173.35249 | P51: 171.46131 | Q51: 169.59329 | R51: 167.7481
B52: Less: Non Controling Interest | D52: =D37 -> 96
B53: DCF value of Common Equity | D53: =D49-D50+D51-D52 -> 181421.28
B54: No. of shares o/s-Diluted | D54: =D39 -> 1384.6328
B55: DCF value per share | D55: =D53/D54 -> 131.02483

Sheet DCF Summary
B2: PepsiCo DCF Valuation — Summary of Steps
B3: (in USD million except per-share data). Walkthrough of how the model gets from forecasts to value per share.
B5: PART A — BUILDING THE FORECAST (the supporting sheets)
B6: Step | C6: What happens | D6: Where
B7: 1. Revenue | C7: Start with revenue, broken into 7 segments. Forecast organic growth and strip out special/one-off items after reconciling them to the filings. | D7: Revenue Segments
B8: 2. Income Statement | C8: Forecast each P&L line as a % of sales, EXCEPT schedule-driven lines (interest, depreciation, amortisation) which come from the asset/debt schedules. | D8: PepsiCo-IS
B9: 3. Fixed Assets / Net Block | C9: From history, back out PPE turnover, depreciation rate and amortisation rate. For forecast years: use PPE turnover × sales to size required PPE, then derive depreciation and net additions (capex). Link forecast depreciation & amortisation back into the I/S. | D9: Fixed Assets Schedule
B10: 4. Cash Flow – CFO | C10: Start from net income, add back D&A and stock-based comp (projected as a % of SG&A), then layer in changes in operating working capital from the balance sheet. | D10: PepsiCo-CFS / PepsiCo-BS
B11: 5. Cash Flow – CFI | C11: Capital expenditure — the additions to tangible and intangible assets from the Fixed Assets Schedule, carried in with a negative sign. | D11: PepsiCo-CFS
B12: 6. Cash Flow – CFF | C12: Financing items (debt movements, dividends, buybacks). Debt detail is captured in the Debt Schedule. | D12: PepsiCo-CFS / Debt Schedule
B14: PART B — THE DCF ENGINE (the DCF sheet)
B15: Step | C15: What happens | D15: Live value
B16: 7. Build FCFF | C16: For each period: EBIT → less tax = NOPAT; add back D&A; add/less change in net working capital; less capex = Debt-Free Cash Flow (Free Cash Flow to Firm). | D16: see DCF rows 10–17
B17: 8. Discount rate (WACC) | C17: Discount at WACC = weight×cost of debt + weight×cost of equity. Cost of equity via CAPM (risk-free + bottom-up beta × ERP). | D17: =WACC!N8 -> 0.052190726
B18: 9. Discount each period | C18: Apply a present-value factor to each period's FCFF (toggle for year-end vs. mid-year discounting), then sum the discounted explicit-period cash flows. | D18: =DCF!G26 -> 34678.952
B19: 10. Terminal value | C19: Gordon growth: final-year FCFF grown at the long-term rate, capitalised by (WACC − g), then discounted back to today. | D19: =DCF!D29 -> 0.0201
B20: 11. Enterprise value | C20: PV of explicit-period FCFF + PV of terminal value = operating enterprise value. | D20: =DCF!D32 -> 260550.05
B21: 12. Bridge to equity | C21: Add non-operating assets; less gross debt & equivalents; add cash; less non-controlling interest = equity value. | D21: =DCF!D38 -> 227314.05
B22: 13. Value per share | C22: Divide equity value by diluted shares outstanding (exact shares on the valuation date, not weighted average). | D22: =DCF!D40 -> 164.16919
B23: 14. Sensitivity | C23: Two-way data table flexing WACC against long-term growth rate to show the range of value per share. | D23: DCF I28:N37
B25: HEADLINE RESULT
B26: DCF value per share | C26: =DCF!D40 -> 164.16919
B27: Implied equity value ($mm) | C27: =DCF!D38 -> 227314.05
B28: Operating enterprise value ($mm) | C28: =DCF!D32 -> 260550.05
B29: WACC / Long-term growth | C29: =TEXT(WACC!N8,"0.0%")&" / "&TEXT(DCF!D29,"0.0%") -> 5.2% / 2.0%

Sheet WACC
B1: PepsiCo WACC Calculation
B2: ='PepsiCo-IS'!A2 -> (in USD million except per Share Data)
D3: 1
B4: Cost of equity | F4: Cost of debt | J4: Weighted average cost of capital
B5: Particulars | C5: Notes | D5: Value | F5: Particulars | G5: Notes | H5: Value | J5: Particulars | K5: Weight | L5: Particulars | M5: Cost | N5: Value
B6: Risk-free rate (%) | C6: Average of YTD | D6: 0.009 | F6: Debt borrowing rate (%) | G6: Rating Based | H6: =D6+D9+0.98% -> 0.0188 | J6: Debt (%) | K6: =D24 -> 0.18440559 | L6: Cost of debt (%) | M6: =H8 -> 0.013724 | N6: =M6*K6 -> 0.0025307824
B7: Beta | C7: =IF(D3=1,B24,B25) -> Bottoms Up beta | D7: =CHOOSE(D3,H24,H25) -> 0.86336171 | F7: Expected income tax rate (%) | G7: Marginal | H7: =DCF!H11 -> 0.27 | J7: Equity (%) | K7: =E24 -> 0.81559441 | L7: Cost of equity (%) | M7: =D10 -> 0.060888039 | N7: =M7*K7 -> 0.049659944
B8: Equity market risk premium (%) | C8: Damodaran ERP | D8: 0.0601 | F8: After-tax cost of debt (%) | H8: =H6*(1-H7) -> 0.013724 | J8: WACC | N8: =SUM(N6:N7) -> 0.052190726
B9: Additional risk premium (%) | D9: 0 | F9: Source: Calculation | J9: Source: Calculation
B10: Cost of equity capital (%) | D10: =D6+D7*D8 -> 0.060888039
B11: Source: Calculation
B14: Calculation of beta
B15: Particulars | C15: Equity beta | D15: D/(D+E) (last three years) | E15: E/(D+E) (last three years) | F15: Tax rate (%) | G15: Unlevered beta | H15: Relevered beta | I15: R sq
B16: Bottom-up | K16: Peers method
B17: ='Beta Calculation'!H5 -> Coca Cola | C17: ='Beta Calculation'!I5 -> 0.90249372 | D17: =AVERAGE($C$32:$C$34)/(AVERAGE($C$32:$C$34)+AVERAGE($F$32:$F$34)) -> 0.20245408 | E17: =1-D17 -> 0.79754592 | F17: =AVERAGE($G$32:$G$34) -> 0.27 | G17: =C17*(E17/(D17*(1-F17)+E17)) -> 0.76140031 | I17: ='Beta Calculation'!J5 -> 0.59193544 | K17: Step 1 | L17: Calculate Levered beta of peer group
B18: ='Beta Calculation'!H10 -> Kraft Heinz | C18: ='Beta Calculation'!I10 -> 0.79741099 | D18: =AVERAGE($C$37:$C$39)/(AVERAGE($C$37:$C$39)+AVERAGE($F$37:$F$39)) -> 0.3821413 | E18: =1-D18 -> 0.6178587 | F18: =AVERAGE($G$37:$G$39) -> 0.27 | G18: =C18*(E18/(D18*(1-F18)+E18)) -> 0.54937033 | I18: ='Beta Calculation'!J10 -> 0.24858799 | K18: Step 2 | L18: unlever beta of peer group companies in 1 using historical capital structure | Q18: = | R18: levBeta*[ Equity / (Equity + Debt(1-t) ]
B19: ='Beta Calculation'!H11 -> Mondelez | C19: ='Beta Calculation'!I11 -> 0.75717638 | D19: =AVERAGE($C$42:$C$44)/(AVERAGE($C$42:$C$44)+AVERAGE($F$42:$F$44)) -> 0.2189331 | E19: =1-D19 -> 0.7810669 | F19: =AVERAGE($G$42:$G$44) -> 0.27 | G19: =C19*(E19/(D19*(1-F19)+E19)) -> 0.62856086 | I19: ='Beta Calculation'!J11 -> 0.51678726 | K19: Step 3 | L19: calc. industry avg of unlevered beta
B20: ='Beta Calculation'!H12 -> Monster Beverage | C20: ='Beta Calculation'!I12 -> 1.0248664 | D20: =AVERAGE($C$47:$C$49)/(AVERAGE($C$47:$C$49)+AVERAGE($F$47:$F$49)) -> 0 | E20: =1-D20 -> 1 | F20: =AVERAGE($G$52:$G$54) -> 0.27 | G20: =C20*(E20/(D20*(1-F20)+E20)) -> 1.0248664 | I20: ='Beta Calculation'!J12 -> 0.48482729 | K20: Step 4 | L20: calc beta of target company by levering the unlevered using the target structure | Q20: = | R20: unlever* [ Equity + Debt(1-t) / Equity ]
F21: Industry Average | G21: =AVERAGE(G17:G20) -> 0.74104947
F22: This is average business risk of the industry
B23: Beta Calculation for Target Co
A24: 1 | B24: Bottoms Up beta | D24: =AVERAGE(C52:C54)/(AVERAGE(C52:C54)+AVERAGE(F52:F54)) -> 0.18440559 | E24: =1-D24 -> 0.81559441 | F24: =AVERAGE(G52:G54) -> 0.27 | G24: =G21 -> 0.74104947 | H24: =G24 * (E24 + D24*(1-F24))/E24 -> 0.86336171
A25: 2 | B25: Regression beta | C25: ='Beta Calculation'!I4 -> 0.7773082 | D25: =D24 -> 0.18440559 | E25: =E24 -> 0.81559441 | F25: =F24 -> 0.27 | G25: Unlevered beta | H25: =C25 -> 0.7773082
B29: Calculation of Capital Structure of Peer Group Companies
C30: Debt | D30: Equity
B31: =B17 -> Coca Cola | D31: Share Price | E31: Shares O/S | F31: M.Cap | G31: Tax Rate
B32: 44008 | C32: =9423+5181+37729 -> 52333 | D32: 43.22 | E32: =4295438919/10^6 -> 4295.4389 | F32: =D32*E32 -> 185648.87 | G32: 0.27
B33: 43644 | C33: =13030+2749+29296 -> 45075 | D33: 48.9 | E33: =4276027437/10^6 -> 4276.0274 | F33: =D33*E33 -> 209097.74 | G33: 0.27
B34: 43280 | C34: =14715+4023+28063 -> 46801 | D34: 40.76 | E34: =4252922447/10^6 -> 4252.9224 | F34: =D34*E34 -> 173349.12 | G34: 0.27
B36: =B18 -> Kraft Heinz
B37: 44009 | C37: =6+757+28097 -> 28860 | D37: 30.9 | E37: =1222578592/10^6 -> 1222.5786 | F37: =D37*E37 -> 37777.678 | G37: 0.27
B38: 43645 | C38: =1+1298+29832 -> 31131 | D38: 31.04 | E38: =1219991425/10^6 -> 1219.9914 | F38: =D38*E38 -> 37868.534 | G38: 0.27
B39: 43281 | C39: =34+2754+31380 -> 34168 | D39: 62.82 | E39: =1219248231/10^6 -> 1219.2482 | F39: =D39*E39 -> 76593.174 | G39: 0.27
B41: =B19 -> Mondelez
B42: 44012 | C42: =2755+945+16004+479 -> 20183 | D42: 51.13 | E42: =1428338344/10^6 -> 1428.3383 | F42: =D42*E42 -> 73030.94 | G42: 0.27
B43: 43646 | C43: =3780+3675+11764 -> 19219 | D43: 53.9 | E43: =1442150501/10^6 -> 1442.1505 | F43: =D43*E43 -> 77731.912 | G43: 0.27
B44: 43281 | C44: =4074+780+14857 -> 19711 | D44: 41 | E44: =1466560999/10^6 -> 1466.561 | F44: =D44*E44 -> 60129.001 | G44: 0.27
B46: =B20 -> Monster Beverage
B47: 44012 | C47: 0 | D47: 69.32 | E47: =527396445/10^6 -> 527.39644 | F47: =D47*E47 -> 36559.122 | G47: 0.27
B48: 43646 | C48: 0 | D48: 63.83 | E48: =544879342/10^6 -> 544.87934 | F48: =D48*E48 -> 34779.648 | G48: 0.27
B49: 43281 | C49: 0 | D49: 57.3 | E49: =552523130/10^6 -> 552.52313 | F49: =D49*E49 -> 31659.575 | G49: 0.27
B51: PepsiCo
B52: 43995 | C52: =6607+38371 -> 44978 | D52: 129 | E52: =1384632842/10^6 -> 1384.6328 | F52: =D52*E52 -> 178617.64 | G52: 0.27
B53: 43631 | C53: =3473+27712 -> 31185 | D53: 132.73 | E53: =1398169503/10^6 -> 1398.1695 | F53: =D53*E53 -> 185579.04 | G53: 0.27
B54: 43267 | C54: =9955+30638 -> 40593 | D54: 107.61 | E54: =1414321635/10^6 -> 1414.3216 | F54: =D54*E54 -> 152195.15 | G54: 0.27
B59: For US companies
B60: Equity Risk Premium (Er - Rf)
B61: Approach 1 | C61: Historical Returns upto 50 years
B62: Approach 2 | C62: Based on Expected (survey)
B63: Approach 3 | C63: Predective Model
B65: Approach 4 | C65: ERP (Matured Market) + Country Risk Premium

Sheet STEP BY STEP
C4: FORMAT where 3.5 years of data already available | I4: Till 13th June 2020
C6: Start with Revenue
D7: Break down revenue (in this case into 7 segments)
D8: Forcast organic growth and ignore special items after reconciling them from the financial reports
C10: Go down the I/S forecasting each item as a % of sales EXCEPT Schedule related lines like interest/ammortization/depr expense
C12: Move to net block Schedule
D13: For previous years to get PPE Turnover(for addition of PPE which justifies sales growth) and Depr rate
E14: Get opening and closing and depr from reports
E15: Get depreciation
E16: back calculate depr then depr rate and PPE Turnover
E17: Do same for ammort and get ammortization rate | J17: But here intangible does not support sales so turnover NOT calculated so how do we get ? WE ASSUME NO NET ADDITION (which happen through acq and merg)
D18: For Forcast years
E19: Use PPE Turnover and sales to get required PPE | J19: This is BEFORE Depr
E20: You can now get depr from depr rate and ppe and net addition from opening and PPE ( so two tasks after previous step)
AH21: Kd | AI21: PRE TAX COST OF DEBT | AL21: Current Cost of Issuing new long term debt ,not historical interest rates ,since WACC is used for future CF discounting
E22: Now link the forcasted depr expenses to I/S | J22: In this case the depr expense is split into Depr expense and Coporate depr and amort(yes I know amort in depr) exp | U22: Use historical ratio to forcast and back calculate split | Z22: Don’t forget /2 for 6 months | AI22: 3 ways | AR22: But if current and not historical then what if earlier 6% and now 10%? How do we realize the advantage
E23: For ammortizable assets directly ammortize the opening balance after assuming 0 new addition and link to I/S | AI23: 1 | AJ23: Recent Debt issued by company | AS23: the 4% saved over the periods will be discounted and reflected in MARKET VALUE OF DEBT ( earlier 100M but saved 4M say over 5 years so now MV of Debt is now 100-17.5 = 82.5
AI24: 2 | AJ24: Rating based default spread (Country + Company) + Risk Free rate
AI25: 3 | AJ25: Current Bond Yeild on Companys Debt Given they trade on the market
AK26: The price will change due to demand and YTM will converge to the current debt interest rate
C27: Leave Debt Schedule for now and move to CashFlowStatement | AL27: (if debt interest rate is higher why would I invest in company bond -> Price drop of bond -> YTM increase to match
AL28: (if bond YTM is higher why would I invest in Debt Funds -> Price increase of bond -> YTM decreases to match
C29: CashFlowStatement
D30: CFO | M30: Interest COST here only as not added back after taking NI (NI already inclused interest as a cost)
E31: Start from netIncome import from I/S
E32: add back depr and ammort | AH32: T | AI32: TAX RATE
E33: for share based compensation (which is to be added back since it’s a non cash expese) project it as a % of SG&A from previous years from I/S and then import it in CFS | AI33: Always marginal Rate which is Taxed on the NEXT unit of earnings | AP33: WACC is forward looking
E34: Change in operating assets will come from B/S | J34: Move to B/S for now for 4 items | AI34: NOT average effective rate of Tax
E37: B/S Working Balance for CFO only (rest later) | AH37: D/V | AI37: Weightage of debt
F38: Accounts reciavble, Inventories, Prepaid expenses are Operating current assets | AI38: Debt includes all INTEREST BEARING liabilities (st+lt+capital leases)
F39: Accounts payable and other current liabetes is Operating current Liabilities | N39: the whole group IS SPLIT INTO 2 OPERATING AND NON OPERATING | AI39: includes Asset DEFECIT for employee benefit obligation | AO39: Pension Obligation > Assets to fund Obligation | AT39: Underfunded Pension Liability treated as liability
AI40: includes Operating leases if capitalized | AM40: It represents fixed contractual payment over a long term period of financing. So very similar to borrowing treated as liability
F41: Project these 4 items through DPO DSO DIO and %age of sales (for prepaid expenses)
F42: Link them first to the top of B/S where it actually is supposed to be | M42: For acc payable you need to first input in the split area where non operating part is STILL TO BE PROJECTED and then back to the main b/s but right now only Operating is used so youre gucci | AI42: TARGET CAPITAL STRUCTURE USED NOT CURRENT | AO42: Forward looking
F43: THEN calculate CHANGES IN B/S ITEMS in CFO | M43: Here just do subtraction from previous period (6month - 1year allowed, makes sense)
AI44: Market value of debt used which depends on current interest rate | AP44: Because investors want required return demanded TODAY
F45: CFO READY
D47: CFI | AH47: Rf
E48: Only one item there i.e. Capex | AI48: Country bond rates + moodys default spread according to country | AQ48: if govt bond rate not there . GDP growth can act as good proxy
E49: Already projected in Fixed Asset Schedule (ADDITION OF ASSETS of BOTH TANGIBLE AND INTANGIBLE but here will come with a negative sign) | S49: Although addition of intangible was assumed to be zero | AI49: 10/20/30 year chosen depending on the DCF forecast period
AI51: (in valuations technically infinite period bond yeild should be used, but 10 years is usually used)
AI53: Real or nominal?
D54: CFF | AJ54: Depends on the cash flow of the company. Use same
E55: Items like
F56: Cash dividends paid
G57: Divident per share in I/S from projecting Divident payout ratio from Divident per share and Earnings per share from previous years | AH57: Beta
G58: now link after multiplying number of shares WITH A MINUS SIGN SINCE OUTFLOW | AI58: Risk related to MacroEconomic Scale
AI59: Includes Business Risk AND Leverage Risk | AY59: Check Beta Calculation Tab
F60: Debt raised / repaid | I60: Only after cash position of the company is know. Does the company need to take raise debt to obtain cash. So for CFF we need debt schedule and for debt schedule we need CFF | AH60: 2 ways
G61: To tackle this we will split CFF into cash BEFORE raising and repaying debt | AH61: 1 | AI61: Covariance and var
G62: Based on that we will judge if the company has taken debt | AH62: 2 | AI62: peers comparison
AH66: ERP
C67: Debt Schedule | AH67: 1 | AI67: Historical indices
D68: Calculate Cash Available for Dicretionary Use (used to predict debt raised/repayed) | S68: Opening cash balance in Discretionary cash available is still left to be projected so Debt Raised/Repaid will change | AH68: 2 | AI68: Survey on expexted
E69: Start with cash BEFORE debt raising and repayment
E70: get opening cash balance from BS (Cash and equivalents) | AI70: ERP of Country = Matured market ERP + Country Risk Premium
E71: Min cash required in bank for safety net(assume 2% of sales)
E72: You get cash available for all debt including mandatory and discretionary repayment of debt
E74: You need to less mandatory debt repayment to get Cash available for discretionary use
F75: In the financial notes, it is mentioned when the mandatory debts are to be repaid. Sum them up for each period (from 2020[6months] to 2024)
G76: Sum if repayment date is less than or equal to the period | Q76: use sumif
G77: Then you will get cumulative debt till period
G78: Subtract all previous years to get for that specefic date | M78: Debt REPAYMENT hence -ve sign | Q78: use - sum(fixedcell:dynamiccell) | AH78: DCF VALUATION
G79: add all and you get discretionary use
AI80: discount 4.5 years
D81: Discretionary debt schedule | AI81: discount terminal value
E82: Total Debt
F83: From B/S Short term + Long Term liabilities | AI83: Add non operating value
E84: Total Mandatory Debt | AJ84: Investments in non controlled affiliates (Most recent)
F85: From Financial Notes
AG86: You get | AH86: Firm Value
E87: From Total Debt - Total Mandatory Debt = Opening Balance for Discretionary Debt | AG87: To get Equity value subtract claims of other stakeholders | AM87: link from 13th June 2020 as it’s the latest Confirmed
E89: Opening balance for Discretionary Debt FY 2020 is Calculated = 3232 | AG89: You get | AH89: Equity Vaue
AG90: Get Exact shares on that day from Notes
E91: Raise debt if Discretionary Cash available is -ve | J91: (raised would be +ve)
E92: Repay Debt to the extent of opening balance if cash +ve | K92: (repaid would be -ve)
E93: Adjust closing balance of discretionary debt and obviously link to the opening of next year
D96: Interest Cost for Mandatory Debt for Debt accumulated till 13th June with different ammount and diff Interest rate | P96: Repayment Date | R96: PeriodStartDate | T96: Debt Accrued till 13jun2020 | X96: 5 things needed for calculation
R97: PeriodEndDate | T97: InterestRate for That particular debt
K98: Interest
E99: Case1 | F99: Repayment date < period start date | K99: 0
E100: Case2 | F100: period start < Repayment date < period end | K100: only interest from period start to repayment
E101: Case3 | F101: period end < Repayment date | K101: Normal interest = principal * rate | P101: if 6 months divide by 2 | S101: Be attentive of Edge cases
D105: Interest Cost for Discretionary Debt
E106: Interest rate used as an average of Mandatory since not given
E108: Okay now theres a problem of circular reference | J108: Interest expense(Debt Balance*Interest Rate) -> Income statement -> Net Income -> CashFlowStatement -> Cash available before debt -> Cash available for discretionary use -> Debt Raised/Repaid -> Closing Balance of debt -> Interest Expense
E109: To solve this. We should charge interest on the opening balance because
F110: Original Setup is Intrest Expese is on Closing Debt where Closing Debt depends on Cash generated which depends on net income which depends on Interest Expense basically all the elements of the loop
F111: New Setup is on Opening Balance which is already known and decided from Previous Years Closing Balance so technically a static number for THAT year. So now no loop
G112: Opening Debt -> Interest -> NI -> Cash -> Closing Debt
G113: No loop
F115: Only assumption to take care here is that all the changed to the debt are happening at the end of the period ( adding/repaying)
D118: Interest Income from having minimum cash balance (2% of sales) (assumed to be invested in 10YR Govt Bond rate)
D121: NOW LINK INTEREST COST TO THE INCOME STATEMENT
E122: Interest Expense Normalized (I/S) = Interest cost for Mandatory + Discretionary | N122: negative sign
E123: Interest Income from Cash Reserved (2% of sales)
D125: NOW LINK DEBT RAISED/REPAYED TO CASH FLOW STATEMENT
E126: Debt Raised would be +ve inflow of cash | K126: Debt Raised only in Discretionary | O126: No debt raised in Mandatory only Repayment
E127: Debt Repaid would be -ve | K127: Mandatory Debt Repayment + Discretionary Repayment
D130: CFI
...

Sheet Beta Calculation
B2: Competitors List as per PepsiCo Filing | H2: Beta calculation
B3: Comeptitor Name | E3: Geography | F3: M.Cap (bn USD) | H3: Name | I3: Beta | J3: R sq
A4: 1 | B4: The Coca-Cola Company | E4: USA | F4: 210 | H4: =B19 -> PepsiCo | I4: =_xlfn.COVARIANCE.P($C$22:$C$178,$U$22:$U$178)/_xlfn.VAR.P($U$22:$U$178) -> 0.7773082 | J4: =RSQ($C$22:$C$178,$U$22:$U$178) -> 0.52038993
A5: 2 | B5: Campbell Soup Company | E5: USA | F5: 14.6 | H5: =D19 -> Coca Cola | I5: =_xlfn.COVARIANCE.P($E$22:$E$178,$U$22:$U$178)/_xlfn.VAR.P($U$22:$U$178) -> 0.90249372 | J5: =RSQ($E$22:$E$178,$U$22:$U$178) -> 0.59193544
A6: 3 | B6: Conagra Brands | E6: USA | F6: 18 | H6: =F19 -> Campbell | I6: =_xlfn.COVARIANCE.P($G$22:$G$178,$U$22:$U$178)/_xlfn.VAR.P($U$22:$U$178) -> 0.3010841 | J6: =RSQ($G$22:$G$178,$U$22:$U$178) -> 0.042397392 | K6: Not enough Explained by market | L6: Ignored in Bottom up Beta Calculation
A7: 4 | B7: Kellogg Company | E7: USA | F7: 22.3 | H7: =H19 -> Conagra | I7: =_xlfn.COVARIANCE.P($I$22:$I$178,$U$22:$U$178)/_xlfn.VAR.P($U$22:$U$178) -> 0.61515834 | J7: =RSQ($I$22:$I$178,$U$22:$U$178) -> 0.13915576
A8: 5 | B8: Keurig Dr Pepper | E8: USA | F8: 39.4 | H8: =J19 -> Kellogg | I8: =_xlfn.COVARIANCE.P($K$22:$K$178,$U$22:$U$178)/_xlfn.VAR.P($U$22:$U$178) -> 0.4788202 | J8: =RSQ($K$22:$K$178,$U$22:$U$178) -> 0.17266424
A9: 6 | B9: The Kraft Heinz Company | E9: USA | F9: 37.5 | H9: =L19 -> Keurig Dr Pepper | I9: =_xlfn.COVARIANCE.P($M$22:$M$178,$U$22:$U$178)/_xlfn.VAR.P($U$22:$U$178) -> 0.2430946 | J9: =RSQ($M$22:$M$178,$U$22:$U$178) -> 0.00027444679
A10: 7 | B10: Link Snacks, Inc | F10: Private | H10: =N19 -> Kraft Heinz | I10: =_xlfn.COVARIANCE.P($O$22:$O$178,$U$22:$U$178)/_xlfn.VAR.P($U$22:$U$178) -> 0.79741099 | J10: =RSQ($O$22:$O$178,$U$22:$U$178) -> 0.24858799
A11: 8 | B11: Mondelēz International | E11: USA | F11: 80.11 | H11: =P19 -> Mondelez | I11: =_xlfn.COVARIANCE.P($Q$22:$Q$178,$U$22:$U$178)/_xlfn.VAR.P($U$22:$U$178) -> 0.75717638 | J11: =RSQ($Q$22:$Q$178,$U$22:$U$178) -> 0.51678726
A12: 9 | B12: Monster Beverage Corporation | E12: USA | F12: 40.9 | H12: =R19 -> Monster Beverage | I12: =_xlfn.COVARIANCE.P($S$22:$S$178,$U$22:$U$178)/_xlfn.VAR.P($U$22:$U$178) -> 1.0248664 | J12: =RSQ($S$22:$S$178,$U$22:$U$178) -> 0.48482729
A13: 10 | B13: Nestlé S.A. | E13: Europe | F13: 301
A14: 11 | B14: Red Bull GmbH | E14: Europe | F14: Private
B15: Source: 10K Dec 2019, Pg 9
A19: Date | B19: PepsiCo | D19: Coca Cola | F19: Campbell | H19: Conagra | J19: Kellogg | L19: Keurig Dr Pepper | N19: Kraft Heinz | P19: Mondelez | R19: Monster Beverage | T19: S&P 500
B20: Price | C20: % | D20: Price | E20: % | F20: Price | G20: % | H20: Price | I20: % | J20: Price | K20: % | L20: Price | M20: % | N20: Price | O20: % | P20: Price | Q20: % | R20: Price | S20: % | T20: Price | U20: %
A21: 43003 | B21: 101.79427 | D21: 40.75935 | F21: 42.145782 | H21: 31.164028 | J21: 56.095238 | L21: 13.319406 | N21: 67.020523 | P21: 37.858841 | R21: 55.25 | T21: 2519.3601
A22: 43010 | B22: 100.85334 | C22: =B22/B21-1 -> -0.0092434087 | D22: 41.194016 | E22: =D22/D21-1 -> 0.010664203 | F22: 41.839733 | G22: =F22/F21-1 -> -0.0072616757 | H22: 31.478077 | I22: =H22/H21-1 -> 0.010077292 | J22: 56.122223 | K22: =J22/J21-1 -> 0.00048105688 | L22: 13.287788 | M22: =L22/L21-1 -> -0.0023738296 | N22: 67.564987 | O22: =N22/N21-1 -> 0.0081238399 | P22: 38.505268 | Q22: =P22/P21-1 -> 0.017074664 | R22: 55.369999 | S22: =R22/R21-1 -> 0.0021719276 | T22: 2549.3301 | U22: =T22/T21-1 -> 0.011895866
A23: 43017 | B23: 102.88137 | C23: =B23/B22-1 -> 0.020108714 | D23: 41.818855 | E23: =D23/D22-1 -> 0.015168198 | F23: 41.569683 | G23: =F23/F22-1 -> -0.0064543911 | H23: 31.708986 | I23: =H23/H22-1 -> 0.0073355498 | J23: 55.72649 | K23: =J23/J22-1 -> -0.0070512709 | L23: 13.436839 | M23: =L23/L22-1 -> 0.011217142 | N23: 67.184715 | O23: =N23/N22-1 -> -0.0056282406 | P23: 39.020153 | Q23: =P23/P22-1 -> 0.013371807 | R23: 55.830002 | S23: =R23/R22-1 -> 0.0083078022 | T23: 2553.1699 | U23: =T23/T22-1 -> 0.0015062169
A24: 43024 | B24: 101.95872 | C24: =B24/B23-1 -> -0.0089681348 | D24: 41.999969 | E24: =D24/D23-1 -> 0.0043309172 | F24: 41.699726 | G24: =F24/F23-1 -> 0.0031283135 | H24: 31.321049 | I24: =H24/H23-1 -> -0.012234292 | J24: 55.267807 | K24: =J24/J23-1 -> -0.0082309688 | L24: 13.403714 | M24: =L24/L23-1 -> -0.0024652375 | N24: 66.294579 | O24: =N24/N23-1 -> -0.013249085 | P24: 38.402283 | Q24: =P24/P23-1 -> -0.015834638 | R24: 56.459999 | S24: =R24/R23-1 -> 0.011284202 | T24: 2575.21 | U24: =T24/T23-1 -> 0.0086324215
A25: 43031 | B25: 101.03604 | C25: =B25/B24-1 -> -0.0090495058 | D25: 41.719242 | E25: =D25/D24-1 -> -0.0066839811 | F25: 43.659088 | G25: =F25/F24-1 -> 0.046987407 | H25: 31.117847 | I25: =H25/H24-1 -> -0.0064877137 | J25: 54.197514 | K25: =J25/J24-1 -> -0.019365578 | L25: 12.909904 | M25: =L25/L24-1 -> -0.036841281 | N25: 66.804466 | O25: =N25/N24-1 -> 0.0076912322 | P25: 38.083977 | Q25: =P25/P24-1 -> -0.008288726 | R25: 56.75 | S25: =R25/R24-1 -> 0.0051363975 | T25: 2581.0701 | U25: =T25/T24-1 -> 0.0022755842
A26: 43038 | B26: 100.68892 | C26: =B26/B25-1 -> -0.0034356255 | D26: 41.628681 | E26: =D26/D25-1 -> -0.002170725 | F26: 42.162354 | G26: =F26/F25-1 -> -0.034282301 | H26: 31.321049 | I26: =H26/H25-1 -> 0.006530079 | J26: 55.72649 | K26: =J26/J25-1 -> 0.028211183 | L26: 12.890328 | M26: =L26/L25-1 -> -0.0015163552 | N26: 67.409416 | O26: =N26/N25-1 -> 0.0090555323 | P26: 38.355476 | Q26: =P26/P25-1 -> 0.0071289561 | R26: 57.669998 | S26: =R26/R25-1 -> 0.016211419 | T26: 2587.8401 | U26: =T26/T25-1 -> 0.0026229509
A27: 43045 | B27: 103.00014 | C27: =B27/B26-1 -> 0.022954045 | D27: 42.144855 | E27: =D27/D26-1 -> 0.01239948 | F27: 43.01503 | G27: =F27/F26-1 -> 0.020223634 | H27: 32.347137 | I27: =H27/H26-1 -> 0.032760333 | J27: 58.190834 | K27: =J27/J26-1 -> 0.044222128 | L27: 12.995719 | M27: =L27/L26-1 -> 0.008175975 | N27: 68.895882 | O27: =N27/N26-1 -> 0.022051311 | P27: 39.272938 | Q27: =P27/P26-1 -> 0.023919974 | R27: 61.16 | S27: =R27/R26-1 -> 0.06051677 | T27: 2582.3 | U27: =T27/T26-1 -> -0.0021407965
A28: 43052 | B28: 104.76324 | C28: =B28/B27-1 -> 0.017117453 | D28: 41.393238 | E28: =D28/D27-1 -> -0.017834134 | F28: 45.101383 | G28: =F28/F27-1 -> 0.048502884 | H28: 33.192993 | I28: =H28/H27-1 -> 0.026149331 | J28: 58.784435 | K28: =J28/J27-1 -> 0.010200936 | L28: 13.137236 | M28: =L28/L27-1 -> 0.010889509 | N28: 68.818108 | O28: =N28/N27-1 -> -0.0011288628 | P28: 39.600594 | Q28: =P28/P27-1 -> 0.0083430478 | R28: 62.169998 | S28: =R28/R27-1 -> 0.016514029 | T28: 2578.8501 | U28: =T28/T27-1 -> -0.0013359993
A29: 43059 | B29: 105.87775 | C29: =B29/B28-1 -> 0.010638369 | D29: 41.547176 | E29: =D29/D28-1 -> 0.0037189166 | F29: 41.763226 | G29: =F29/F28-1 -> -0.074014515 | H29: 32.960613 | I29: =H29/H28-1 -> -0.0070008752 | J29: 58.397701 | K29: =J29/J28-1 -> -0.0065788503 | L29: 13.031851 | M29: =L29/L28-1 -> -0.0080218548 | N29: 69.481682 | O29: =N29/N28-1 -> 0.0096424331 | P29: 39.460175 | Q29: =P29/P28-1 -> -0.0035458812 | R29: 61.75 | S29: =R29/R28-1 -> -0.006755638 | T29: 2602.4199 | U29: =T29/T28-1 -> 0.0091396642
A30: 43066 | B30: 106.68164 | C30: =B30/B29-1 -> 0.0075926625 | D30: 41.628681 | E30: =D30/D29-1 -> 0.0019617458 | F30: 44.647827 | G30: =F30/F29-1 -> 0.069070359 | H30: 34.828945 | I30: =H30/H29-1 -> 0.056683776 | J30: 59.351051 | K30: =J30/J29-1 -> 0.016325129 | L30: 13.588897 | M30: =L30/L29-1 -> 0.042744964 | N30: 70.744835 | O30: =N30/N29-1 -> 0.018179655 | P30: 40.181034 | Q30: =P30/P29-1 -> 0.018268013 | R30: 62.919998 | S30: =R30/R29-1 -> 0.018947336 | T30: 2642.22 | U30: =T30/T29-1 -> 0.015293477
A31: 43073 | B31: 107.22859 | C31: =B31/B30-1 -> 0.0051269459 | D31: 41.367416 | E31: =D31/D30-1 -> -0.0062760816 | F31: 44.402908 | G31: =F31/F30-1 -> -0.0054855749 | H31: 34.624447 | I31: =H31/H30-1 -> -0.0058714957 | J31: 60.324379 | K31: =J31/J30-1 -> 0.016399507 | L31: 14.174546 | M31: =L31/L30-1 -> 0.043097611 | N31: 68.366631 | O31: =N31/N30-1 -> -0.033616645 | P31: 39.928261 | Q31: =P31/P30-1 -> -0.0062908535 | R31: 63.220001 | S31: =R31/R30-1 -> 0.0047680071 | T31: 2651.5 | U31: =T31/T30-1 -> 0.0035122091
A32: 43080 | B32: 109.66622 | C32: =B32/B31-1 -> 0.022733023 | D32: 42.170834 | E32: =D32/D31-1 -> 0.019421518 | F32: 44.983456 | G32: =F32/F31-1 -> 0.013074549 | H32: 35.098495 | I32: =H32/H31-1 -> 0.013691136 | J32: 58.92802 | K32: =J32/J31-1 -> -0.023147507 | L32: 14.139918 | M32: =L32/L31-1 -> -0.0024429707 | N32: 69.290047 | O32: =N32/N31-1 -> 0.013506823 | P32: 40.611683 | Q32: =P32/P31-1 -> 0.017116248 | R32: 64.010002 | S32: =R32/R31-1 -> 0.012496061 | T32: 2675.8101 | U32: =T32/T31-1 -> 0.0091684175
A33: 43087 | B33: 109.09591 | C33: =B33/B32-1 -> -0.0052004436 | D33: 41.623047 | E33: =D33/D32-1 -> -0.012989712 | F33: 44.239632 | G33: =F33/F32-1 -> -0.016535501 | H33: 35.395947 | I33: =H33/H32-1 -> 0.0084747793 | J33: 61.747932 | K33: =J33/J32-1 -> 0.0478535 | L33: 14.560826 | M33: =L33/L32-1 -> 0.029767358 | N33: 68.157578 | O33: =N33/N32-1 -> -0.016343891 | P33: 40.592957 | Q33: =P33/P32-1 -> -0.00046109884 | R33: 63.77 | S33: =R33/R32-1 -> -0.0037494453 | T33: 2683.3401 | U33: =T33/T32-1 -> 0.0028141119
... A178: 44102 | B178: 137.16 | C178: =B178/B177-1 -> 0.027031081 | D178: 48.919998 | E178: =D178/D177-1 -> 0.0041050287 | F178: 47.674034 | G178: =F178/F177-1 -> 0.0096719532 | H178: 35.48 | I178: =H178/H177-1 -> 0.010250598 | J178: 63.439999 | K178: =J178/J177-1 -> 0.0057069909 | L178: 26.962664 | M178: =L178/L177-1 -> -0.027618286 | N178: 29.59 | O178: =N178/N177-1 -> 0.015791315 | P178: 56.167927 | Q178: =P178/P177-1 -> 0.0056979718 | R178: 79.790001 | S178: =R178/R177-1 -> 0.012691966 | T178: 3335.47 | U178: =T178/T177-1 -> 0.011220391

Sheet Debt Schedule
A1: PepsiCo Inc.
A2: ='PepsiCo-IS'!A2 -> (in USD million except per Share Data)
A3: Debt Schedule | B3: ='PepsiCo-CFS'!B3 -> 6 | C3: ='PepsiCo-CFS'!C3 -> 12 | D3: ='PepsiCo-CFS'!D3 -> 12 | E3: ='PepsiCo-CFS'!E3 -> 12 | F3: ='PepsiCo-CFS'!F3 -> 12 | G3: 12
B4: ='PepsiCo-CFS'!B4 -> 44196 | C4: ='PepsiCo-CFS'!C4 -> 44561 | D4: ='PepsiCo-CFS'!D4 -> 44926 | E4: ='PepsiCo-CFS'!E4 -> 45291 | F4: ='PepsiCo-CFS'!F4 -> 45657 | G4: =EOMONTH(F4,12) -> 46022
A6: Cash Before Debt | B6: ='PepsiCo-CFS'!B25 -> 4247.5556 | C6: ='PepsiCo-CFS'!C25 -> 4183.773 | D6: ='PepsiCo-CFS'!D25 -> 2792.5156 | E6: ='PepsiCo-CFS'!E25 -> 2873.1876 | F6: ='PepsiCo-CFS'!F25 -> 2937.039 | G6: What we got after yearly operations before debt repay and raise
A7: Add: Opening Cash Balance | B7: ='PepsiCo-BS'!E5 -> 8927 | C7: ='PepsiCo-BS'!F5 -> 7824.5556 | D7: ='PepsiCo-BS'!G5 -> 8732.3285 | E7: ='PepsiCo-BS'!H5 -> 7693.8441 | F7: ='PepsiCo-BS'!I5 -> 8295.0317 | G7: What we had before
A8: Less: Minimum Cash Required | B8: =-$G$8*'PepsiCo-IS'!J6 -> -1378.032 | C8: =-$G$8*'PepsiCo-IS'!K6 -> -1433.5658 | D8: =-$G$8*'PepsiCo-IS'!L6 -> -1492.1558 | E8: =-$G$8*'PepsiCo-IS'!M6 -> -1553.9942 | F8: =-$G$8*'PepsiCo-IS'!N6 -> -1619.2862 | G8: 0.02 | H8: of Sales | I8: Not mentioned here. Taken as average of 500 companies
A9: Cash Available for Debt | B9: =SUM(B6:B8) -> 11796.524 | C9: =SUM(C6:C8) -> 10574.763 | D9: =SUM(D6:D8) -> 10032.688 | E9: =SUM(E6:E8) -> 9013.0375 | F9: =SUM(F6:F8) -> 9612.7846
A10: Less: Mandatory Debt Repayments | B10: =-SUMIF($B$17:$B$33,"<="&B4,$I$17:$I$33) -> -2118 | C10: =-SUMIF($B$17:$B$33,"<="&C4,$I$17:$I$33)-SUM($B$10:B10) -> -3276 | D10: =-SUMIF($B$17:$B$33,"<="&D4,$I$17:$I$33)-SUM($B$10:C10) -> -3831 | E10: =-SUMIF($B$17:$B$33,"<="&E4,$I$17:$I$33)-SUM($B$10:D10) -> -2272 | F10: =-SUMIF($B$17:$B$33,"<="&F4,$I$17:$I$33)-SUM($B$10:E10) -> -2839 | G10: =-SUMIF($B$17:$B$33,"<="&G4,$I$17:$I$33)-SUM($B$10:F10) -> -20410
A11: Cash Available for Discretionery Sweep | B11: =SUM(B9:B10) -> 9678.5236 | C11: =SUM(C9:C10) -> 7298.7627 | D11: =SUM(D9:D10) -> 6201.6883 | E11: =SUM(E9:E10) -> 6741.0375 | F11: =SUM(F9:F10) -> 6773.7846
A12: Source: Calculations
A14: Individual debt raised and its details | M14: Interest Expenses
A15: Mandatory Debt | F15: Balance As on 31 Dec 2019 | G15: During 24 Weeks June 2020 | I15: Net Balance As on 13 June 2020 | M15: =B3 -> 6 | N15: =C3 -> 12 | O15: =D3 -> 12 | P15: =E3 -> 12 | Q15: =F3 -> 12
B16: Repayment Date | C16: Interest Rate | E16: Average Rate | G16: Raised | H16: Repaid | J16: Source | L16: 43995 | M16: =B4 -> 44196 | N16: =C4 -> 44561 | O16: =D4 -> 44926 | P16: =E4 -> 45291 | Q16: =F4 -> 45657
A17: 2020 Notes | B17: 44196 | C17: 0.027 | D17: 0.039 | E17: =AVERAGE(C17:D17) -> 0.033 | F17: 2840 | H17: 750 | I17: =F17+G17-H17 -> 2090 | J17: 10K Dec 2019, Pg 112 | M17: =IF(AND($B17<=M16,$B17>=L$16),($B17-L$16)*$I17*$E17/365,IF($B17<=L$16,0,$I17*$E17*M$15/12)) -> 37.98074 | N17: =IF(AND($B17<=N16,$B17>=M$16),($B17-M$16)*$I17*$E17/365,IF($B17<=M$16,0,$I17*$E17*N$15/12)) -> 0 | O17: =IF(AND($B17<=O16,$B17>=N$16),($B17-N$16)*$I17*$E17/365,IF($B17<=N$16,0,$I17*$E17*O$15/12)) -> 0 | P17: =IF(AND($B17<=P16,$B17>=O$16),($B17-O$16)*$I17*$E17/365,IF($B17<=O$16,0,$I17*$E17*P$15/12)) -> 0 | Q17: =IF(AND($B17<=Q16,$B17>=P$16),($B17-P$16)*$I17*$E17/365,IF($B17<=P$16,0,$I17*$E17*Q$15/12)) -> 0
A18: 2021 Notes | B18: 44561 | C18: 0.024 | D18: 0.031 | E18: =AVERAGE(C18:D18) -> 0.0275 | F18: 3276 | I18: =F18+G18-H18 -> 3276 | J18: 10K Dec 2019, Pg 112 | M18: =IF(AND($B18<=M17,$B18>=L$16),($B18-L$16)*$I18*$E18/365,IF($B18<=L$16,0,$I18*$E18*M$15/12)) -> 45.045 | N18: =IF(AND($B18<=N17,$B18>=M$16),($B18-M$16)*$I18*$E18/365,IF($B18<=M$16,0,$I18*$E18*N$15/12)) -> 90.09 | O18: =IF(AND($B18<=O17,$B18>=N$16),($B18-N$16)*$I18*$E18/365,IF($B18<=N$16,0,$I18*$E18*O$15/12)) -> 0 | P18: =IF(AND($B18<=P17,$B18>=O$16),($B18-O$16)*$I18*$E18/365,IF($B18<=O$16,0,$I18*$E18*P$15/12)) -> 0 | Q18: =IF(AND($B18<=Q17,$B18>=P$16),($B18-P$16)*$I18*$E18/365,IF($B18<=P$16,0,$I18*$E18*Q$15/12)) -> 0
A19: 2022 Notes | B19: 44926 | C19: 0.027 | D19: 0.028 | E19: =AVERAGE(C19:D19) -> 0.0275 | F19: 3831 | I19: =F19+G19-H19 -> 3831 | J19: 10K Dec 2019, Pg 112 | M19: =IF(AND($B19<=M18,$B19>=L$16),($B19-L$16)*$I19*$E19/365,IF($B19<=L$16,0,$I19*$E19*M$15/12)) -> 52.67625 | N19: =IF(AND($B19<=N18,$B19>=M$16),($B19-M$16)*$I19*$E19/365,IF($B19<=M$16,0,$I19*$E19*N$15/12)) -> 105.3525 | O19: =IF(AND($B19<=O18,$B19>=N$16),($B19-N$16)*$I19*$E19/365,IF($B19<=N$16,0,$I19*$E19*O$15/12)) -> 105.3525 | P19: =IF(AND($B19<=P18,$B19>=O$16),($B19-O$16)*$I19*$E19/365,IF($B19<=O$16,0,$I19*$E19*P$15/12)) -> 0 | Q19: =IF(AND($B19<=Q18,$B19>=P$16),($B19-P$16)*$I19*$E19/365,IF($B19<=P$16,0,$I19*$E19*Q$15/12)) -> 0
A20: 2023 Notes | B20: 45291 | C20: 0.028 | D20: 0.029 | E20: =AVERAGE(C20:D20) -> 0.0285 | F20: 1272 | I20: =F20+G20-H20 -> 1272 | J20: 10K Dec 2019, Pg 112 | M20: =IF(AND($B20<=M19,$B20>=L$16),($B20-L$16)*$I20*$E20/365,IF($B20<=L$16,0,$I20*$E20*M$15/12)) -> 18.126 | N20: =IF(AND($B20<=N19,$B20>=M$16),($B20-M$16)*$I20*$E20/365,IF($B20<=M$16,0,$I20*$E20*N$15/12)) -> 36.252 | O20: =IF(AND($B20<=O19,$B20>=N$16),($B20-N$16)*$I20*$E20/365,IF($B20<=N$16,0,$I20*$E20*O$15/12)) -> 36.252 | P20: =IF(AND($B20<=P19,$B20>=O$16),($B20-O$16)*$I20*$E20/365,IF($B20<=O$16,0,$I20*$E20*P$15/12)) -> 36.252 | Q20: =IF(AND($B20<=Q19,$B20>=P$16),($B20-P$16)*$I20*$E20/365,IF($B20<=P$16,0,$I20*$E20*Q$15/12)) -> 0
A21: 2024 Notes | B21: 45657 | C21: 0.034 | D21: 0.032 | E21: =AVERAGE(C21:D21) -> 0.033 | F21: 1839 | I21: =F21+G21-H21 -> 1839 | J21: 10K Dec 2019, Pg 112 | M21: =IF(AND($B21<=M20,$B21>=L$16),($B21-L$16)*$I21*$E21/365,IF($B21<=L$16,0,$I21*$E21*M$15/12)) -> 30.3435 | N21: =IF(AND($B21<=N20,$B21>=M$16),($B21-M$16)*$I21*$E21/365,IF($B21<=M$16,0,$I21*$E21*N$15/12)) -> 60.687 | O21: =IF(AND($B21<=O20,$B21>=N$16),($B21-N$16)*$I21*$E21/365,IF($B21<=N$16,0,$I21*$E21*O$15/12)) -> 60.687 | P21: =IF(AND($B21<=P20,$B21>=O$16),($B21-O$16)*$I21*$E21/365,IF($B21<=O$16,0,$I21*$E21*P$15/12)) -> 60.687 | Q21: =IF(AND($B21<=Q20,$B21>=P$16),($B21-P$16)*$I21*$E21/365,IF($B21<=P$16,0,$I21*$E21*Q$15/12)) -> 60.687
A22: 2025-2049 Notes | B22: 46022 | C22: 0.034 | D22: 0.037 | E22: =AVERAGE(C22:D22) -> 0.0355 | F22: 18910 | I22: =F22+G22-H22 -> 18910 | J22: 10K Dec 2019, Pg 112 | M22: =IF(AND($B22<=M21,$B22>=L$16),($B22-L$16)*$I22*$E22/365,IF($B22<=L$16,0,$I22*$E22*M$15/12)) -> 335.6525 | N22: =IF(AND($B22<=N21,$B22>=M$16),($B22-M$16)*$I22*$E22/365,IF($B22<=M$16,0,$I22*$E22*N$15/12)) -> 671.305 | O22: =IF(AND($B22<=O21,$B22>=N$16),($B22-N$16)*$I22*$E22/365,IF($B22<=N$16,0,$I22*$E22*O$15/12)) -> 671.305 | P22: =IF(AND($B22<=P21,$B22>=O$16),($B22-O$16)*$I22*$E22/365,IF($B22<=O$16,0,$I22*$E22*P$15/12)) -> 671.305 | Q22: =IF(AND($B22<=Q21,$B22>=P$16),($B22-P$16)*$I22*$E22/365,IF($B22<=P$16,0,$I22*$E22*Q$15/12)) -> 671.305
A23: 2019-2026 Notes | B23: 44196 | C23: 0.013 | D23: =C23 -> 0.013 | E23: =AVERAGE(C23:D23) -> 0.013 | F23: 28 | I23: =F23+G23-H23 -> 28 | J23: 10K Dec 2019, Pg 112 | M23: =IF(AND($B23<=M22,$B23>=L$16),($B23-L$16)*$I23*$E23/365,IF($B23<=L$16,0,$I23*$E23*M$15/12)) -> 0.182 | N23: =IF(AND($B23<=N22,$B23>=M$16),($B23-M$16)*$I23*$E23/365,IF($B23<=M$16,0,$I23*$E23*N$15/12)) -> 0 | O23: =IF(AND($B23<=O22,$B23>=N$16),($B23-N$16)*$I23*$E23/365,IF($B23<=N$16,0,$I23*$E23*O$15/12)) -> 0 | P23: =IF(AND($B23<=P22,$B23>=O$16),($B23-O$16)*$I23*$E23/365,IF($B23<=O$16,0,$I23*$E23*P$15/12)) -> 0 | Q23: =IF(AND($B23<=Q22,$B23>=P$16),($B23-P$16)*$I23*$E23/365,IF($B23<=P$16,0,$I23*$E23*Q$15/12)) -> 0
A24: New Notes March 2025 | B24: 45747 | C24: 0.0225 | D24: 0.0225 | E24: =AVERAGE(C24:D24) -> 0.0225 | G24: 1500 | I24: =F24+G24-H24 -> 1500 | J24: 10Q June 2020, Pg 19 | M24: =IF(AND($B24<=M23,$B24>=L$16),($B24-L$16)*$I24*$E24/365,IF($B24<=L$16,0,$I24*$E24*M$15/12)) -> 16.875 | N24: =IF(AND($B24<=N23,$B24>=M$16),($B24-M$16)*$I24*$E24/365,IF($B24<=M$16,0,$I24*$E24*N$15/12)) -> 33.75 | O24: =IF(AND($B24<=O23,$B24>=N$16),($B24-N$16)*$I24*$E24/365,IF($B24<=N$16,0,$I24*$E24*O$15/12)) -> 33.75 | P24: =IF(AND($B24<=P23,$B24>=O$16),($B24-O$16)*$I24*$E24/365,IF($B24<=O$16,0,$I24*$E24*P$15/12)) -> 33.75 | Q24: =IF(AND($B24<=Q23,$B24>=P$16),($B24-P$16)*$I24*$E24/365,IF($B24<=P$16,0,$I24*$E24*Q$15/12)) -> 33.75
A25: New Notes March 2027 | B25: 46477 | C25: 0.02625 | D25: 0.02625 | E25: =AVERAGE(C25:D25) -> 0.02625 | G25: 500 | I25: =F25+G25-H25 -> 500 | J25: 10Q June 2020, Pg 19 | M25: =IF(AND($B25<=M24,$B25>=L$16),($B25-L$16)*$I25*$E25/365,IF($B25<=L$16,0,$I25*$E25*M$15/12)) -> 6.5625 | N25: =IF(AND($B25<=N24,$B25>=M$16),($B25-M$16)*$I25*$E25/365,IF($B25<=M$16,0,$I25*$E25*N$15/12)) -> 13.125 | O25: =IF(AND($B25<=O24,$B25>=N$16),($B25-N$16)*$I25*$E25/365,IF($B25<=N$16,0,$I25*$E25*O$15/12)) -> 13.125 | P25: =IF(AND($B25<=P24,$B25>=O$16),($B25-O$16)*$I25*$E25/365,IF($B25<=O$16,0,$I25*$E25*P$15/12)) -> 13.125 | Q25: =IF(AND($B25<=Q24,$B25>=P$16),($B25-P$16)*$I25*$E25/365,IF($B25<=P$16,0,$I25*$E25*Q$15/12)) -> 13.125
A26: New Notes March 2030 | B26: 47573 | C26: 0.0275 | D26: 0.0275 | E26: =AVERAGE(C26:D26) -> 0.0275 | G26: 1500 | I26: =F26+G26-H26 -> 1500 | J26: 10Q June 2020, Pg 19 | M26: =IF(AND($B26<=M25,$B26>=L$16),($B26-L$16)*$I26*$E26/365,IF($B26<=L$16,0,$I26*$E26*M$15/12)) -> 20.625 | N26: =IF(AND($B26<=N25,$B26>=M$16),($B26-M$16)*$I26*$E26/365,IF($B26<=M$16,0,$I26*$E26*N$15/12)) -> 41.25 | O26: =IF(AND($B26<=O25,$B26>=N$16),($B26-N$16)*$I26*$E26/365,IF($B26<=N$16,0,$I26*$E26*O$15/12)) -> 41.25 | P26: =IF(AND($B26<=P25,$B26>=O$16),($B26-O$16)*$I26*$E26/365,IF($B26<=O$16,0,$I26*$E26*P$15/12)) -> 41.25 | Q26: =IF(AND($B26<=Q25,$B26>=P$16),($B26-P$16)*$I26*$E26/365,IF($B26<=P$16,0,$I26*$E26*Q$15/12)) -> 41.25
A27: New Notes March 2040 | B27: 51226 | C27: 0.035 | D27: 0.035 | E27: =AVERAGE(C27:D27) -> 0.035 | G27: 750 | I27: =F27+G27-H27 -> 750 | J27: 10Q June 2020, Pg 19 | M27: =IF(AND($B27<=M26,$B27>=L$16),($B27-L$16)*$I27*$E27/365,IF($B27<=L$16,0,$I27*$E27*M$15/12)) -> 13.125 | N27: =IF(AND($B27<=N26,$B27>=M$16),($B27-M$16)*$I27*$E27/365,IF($B27<=M$16,0,$I27*$E27*N$15/12)) -> 26.25 | O27: =IF(AND($B27<=O26,$B27>=N$16),($B27-N$16)*$I27*$E27/365,IF($B27<=N$16,0,$I27*$E27*O$15/12)) -> 26.25 | P27: =IF(AND($B27<=P26,$B27>=O$16),($B27-O$16)*$I27*$E27/365,IF($B27<=O$16,0,$I27*$E27*P$15/12)) -> 26.25 | Q27: =IF(AND($B27<=Q26,$B27>=P$16),($B27-P$16)*$I27*$E27/365,IF($B27<=P$16,0,$I27*$E27*Q$15/12)) -> 26.25
A28: New Notes March 2050 | B28: 54878 | C28: 0.03625 | D28: 0.03625 | E28: =AVERAGE(C28:D28) -> 0.03625 | G28: 1500 | I28: =F28+G28-H28 -> 1500 | J28: 10Q June 2020, Pg 19 | M28: =IF(AND($B28<=M27,$B28>=L$16),($B28-L$16)*$I28*$E28/365,IF($B28<=L$16,0,$I28*$E28*M$15/12)) -> 27.1875 | N28: =IF(AND($B28<=N27,$B28>=M$16),($B28-M$16)*$I28*$E28/365,IF($B28<=M$16,0,$I28*$E28*N$15/12)) -> 54.375 | O28: =IF(AND($B28<=O27,$B28>=N$16),($B28-N$16)*$I28*$E28/365,IF($B28<=N$16,0,$I28*$E28*O$15/12)) -> 54.375 | P28: =IF(AND($B28<=P27,$B28>=O$16),($B28-O$16)*$I28*$E28/365,IF($B28<=O$16,0,$I28*$E28*P$15/12)) -> 54.375 | Q28: =IF(AND($B28<=Q27,$B28>=P$16),($B28-P$16)*$I28*$E28/365,IF($B28<=P$16,0,$I28*$E28*Q$15/12)) -> 54.375
A29: New Notes March 2060 | B29: 58531 | C29: 0.03875 | D29: 0.03875 | E29: =AVERAGE(C29:D29) -> 0.03875 | G29: 750 | I29: =F29+G29-H29 -> 750 | J29: 10Q June 2020, Pg 19 | M29: =IF(AND($B29<=M28,$B29>=L$16),($B29-L$16)*$I29*$E29/365,IF($B29<=L$16,0,$I29*$E29*M$15/12)) -> 14.53125 | N29: =IF(AND($B29<=N28,$B29>=M$16),($B29-M$16)*$I29*$E29/365,IF($B29<=M$16,0,$I29*$E29*N$15/12)) -> 29.0625 | O29: =IF(AND($B29<=O28,$B29>=N$16),($B29-N$16)*$I29*$E29/365,IF($B29<=N$16,0,$I29*$E29*O$15/12)) -> 29.0625 | P29: =IF(AND($B29<=P28,$B29>=O$16),($B29-O$16)*$I29*$E29/365,IF($B29<=O$16,0,$I29*$E29*P$15/12)) -> 29.0625 | Q29: =IF(AND($B29<=Q28,$B29>=P$16),($B29-P$16)*$I29*$E29/365,IF($B29<=P$16,0,$I29*$E29*Q$15/12)) -> 29.0625
A30: New Notes May 2023 | B30: 45077 | C30: 0.0075 | D30: 0.0075 | E30: =AVERAGE(C30:D30) -> 0.0075 | G30: 1000 | I30: =F30+G30-H30 -> 1000 | J30: 10Q June 2020, Pg 19 | M30: =IF(AND($B30<=M29,$B30>=L$16),($B30-L$16)*$I30*$E30/365,IF($B30<=L$16,0,$I30*$E30*M$15/12)) -> 3.75 | N30: =IF(AND($B30<=N29,$B30>=M$16),($B30-M$16)*$I30*$E30/365,IF($B30<=M$16,0,$I30*$E30*N$15/12)) -> 7.5 | O30: =IF(AND($B30<=O29,$B30>=N$16),($B30-N$16)*$I30*$E30/365,IF($B30<=N$16,0,$I30*$E30*O$15/12)) -> 7.5 | P30: =IF(AND($B30<=P29,$B30>=O$16),($B30-O$16)*$I30*$E30/365,IF($B30<=O$16,0,$I30*$E30*P$15/12)) -> 7.5 | Q30: =IF(AND($B30<=Q29,$B30>=P$16),($B30-P$16)*$I30*$E30/365,IF($B30<=P$16,0,$I30*$E30*Q$15/12)) -> 0
A31: New Notes May 2030 | B31: 47634 | C31: 0.01625 | D31: 0.01625 | E31: =AVERAGE(C31:D31) -> 0.01625 | G31: 1000 | I31: =F31+G31-H31 -> 1000 | J31: 10Q June 2020, Pg 19 | M31: =IF(AND($B31<=M30,$B31>=L$16),($B31-L$16)*$I31*$E31/365,IF($B31<=L$16,0,$I31*$E31*M$15/12)) -> 8.125 | N31: =IF(AND($B31<=N30,$B31>=M$16),($B31-M$16)*$I31*$E31/365,IF($B31<=M$16,0,$I31*$E31*N$15/12)) -> 16.25 | O31: =IF(AND($B31<=O30,$B31>=N$16),($B31-N$16)*$I31*$E31/365,IF($B31<=N$16,0,$I31*$E31*O$15/12)) -> 16.25 | P31: =IF(AND($B31<=P30,$B31>=O$16),($B31-O$16)*$I31*$E31/365,IF($B31<=O$16,0,$I31*$E31*P$15/12)) -> 16.25 | Q31: =IF(AND($B31<=Q30,$B31>=P$16),($B31-P$16)*$I31*$E31/365,IF($B31<=P$16,0,$I31*$E31*Q$15/12)) -> 16.25
A32: New Notes May 2024 | B32: 45443 | C32: 0.0025 | D32: 0.0025 | E32: =AVERAGE(C32:D32) -> 0.0025 | G32: 1000 | I32: =F32+G32-H32 -> 1000 | J32: 10Q June 2020, Pg 19 | M32: =IF(AND($B32<=M31,$B32>=L$16),($B32-L$16)*$I32*$E32/365,IF($B32<=L$16,0,$I32*$E32*M$15/12)) -> 1.25 | N32: =IF(AND($B32<=N31,$B32>=M$16),($B32-M$16)*$I32*$E32/365,IF($B32<=M$16,0,$I32*$E32*N$15/12)) -> 2.5 | O32: =IF(AND($B32<=O31,$B32>=N$16),($B32-N$16)*$I32*$E32/365,IF($B32<=N$16,0,$I32*$E32*O$15/12)) -> 2.5 | P32: =IF(AND($B32<=P31,$B32>=O$16),($B32-O$16)*$I32*$E32/365,IF($B32<=O$16,0,$I32*$E32*P$15/12)) -> 2.5 | Q32: =IF(AND($B32<=Q31,$B32>=P$16),($B32-P$16)*$I32*$E32/365,IF($B32<=P$16,0,$I32*$E32*Q$15/12)) -> 2.5
A33: New Notes May 2028 | B33: 46904 | C33: 0.005 | D33: 0.005 | E33: =AVERAGE(C33:D33) -> 0.005 | G33: 1000 | I33: =F33+G33-H33 -> 1000 | J33: 10Q June 2020, Pg 19 | M33: =IF(AND($B33<=M32,$B33>=L$16),($B33-L$16)*$I33*$E33/365,IF($B33<=L$16,0,$I33*$E33*M$15/12)) -> 2.5 | N33: =IF(AND($B33<=N32,$B33>=M$16),($B33-M$16)*$I33*$E33/365,IF($B33<=M$16,0,$I33*$E33*N$15/12)) -> 5 | O33: =IF(AND($B33<=O32,$B33>=N$16),($B33-N$16)*$I33*$E33/365,IF($B33<=N$16,0,$I33*$E33*O$15/12)) -> 5 | P33: =IF(AND($B33<=P32,$B33>=O$16),($B33-O$16)*$I33*$E33/365,IF($B33<=O$16,0,$I33*$E33*P$15/12)) -> 5 | Q33: =IF(AND($B33<=Q32,$B33>=P$16),($B33-P$16)*$I33*$E33/365,IF($B33<=P$16,0,$I33*$E33*Q$15/12)) -> 5
A35: Total Mandatory Debt | E35: =AVERAGE(E17:E33) -> 0.024441176 | F35: =SUM(F17:F34) -> 31996 | G35: =SUM(G17:G34) -> 10500 | H35: =SUM(H17:H34) -> 750 | I35: =SUM(I17:I34) -> 41746 | M35: =SUM(M17:M34) -> 634.53724 | N35: =SUM(N17:N34) -> 1192.749 | O35: =SUM(O17:O34) -> 1102.659 | P35: =SUM(P17:P34) -> 997.3065 | Q35: =SUM(Q17:Q34) -> 953.5545
A37: Total Debt (Discretionery + Mandatory) | F37: ='PepsiCo-BS'!D23+'PepsiCo-BS'!D27 -> 32068 | I37: ='PepsiCo-BS'!E23+'PepsiCo-BS'!E27 -> 44978
A39: Discretionary Debt (Balance) | F39: =F37-F35 -> 72 | I39: =I37-I35 -> 3232
A42: Discretionary Debt Schedule | B42: Amount need to be repaid with choice of time
B43: =B3 -> 6 | C43: =C3 -> 12 | D43: =D3 -> 12 | E43: =E3 -> 12 | F43: =F3 -> 12
B44: =B4 -> 44196 | C44: =C4 -> 44561 | D44: =D4 -> 44926 | E44: =E4 -> 45291 | F44: =F4 -> 45657
A45: Opening Balance | B45: =I39 -> 3232 | C45: =B48 -> 0 | D45: =C48 -> 0 | E45: =D48 -> 0 | F45: =E48 -> 0
A46: Add: Debt Raised | B46: =IF(B11<0,-B11,0) -> 0 | C46: =IF(C11<0,-C11,0) -> 0 | D46: =IF(D11<0,-D11,0) -> 0 | E46: =IF(E11<0,-E11,0) -> 0 | F46: =IF(F11<0,-F11,0) -> 0
A47: Less: Debt Repaid | B47: =IF(B11>11,MIN(B45,B11),0) -> 3232 | C47: =IF(C11>11,MIN(C45,C11),0) -> 0 | D47: =IF(D11>11,MIN(D45,D11),0) -> 0 | E47: =IF(E11>11,MIN(E45,E11),0) -> 0 | F47: =IF(F11>11,MIN(F45,F11),0) -> 0
A48: Closing Balance | B48: =B45+B46-B47 -> 0 | C48: =C45+C46-C47 -> 0 | D48: =D45+D46-D47 -> 0 | E48: =E45+E46-E47 -> 0 | F48: =F45+F46-F47 -> 0
A50: Interest Rate | B50: =E35 -> 0.024441176 | C50: Assumed to be average of Mandatory debt as not specified
A52: Interest Expenses | B52: =$B$50*B45*B43/12 -> 39.496941 | C52: =$B$50*C45*C43/12 -> 0 | D52: =$B$50*D45*D43/12 -> 0 | E52: =$B$50*E45*E43/12 -> 0 | F52: =$B$50*F45*F43/12 -> 0
A57: Minimum Cash Balance | B57: =-B8 -> 1378.032 | C57: =-C8 -> 1433.5658 | D57: =-D8 -> 1492.1558 | E57: =-E8 -> 1553.9942 | F57: =-F8 -> 1619.2862
A59: Interest Income Rate | B59: 0.0072
A61: Interest Income | B61: =$B$59*B57*B43/12 -> 4.9609152 | C61: =$B$59*C57*C43/12 -> 10.321674 | D61: =$B$59*D57*D43/12 -> 10.743522 | E61: =$B$59*E57*E43/12 -> 11.188758 | F61: =$B$59*F57*F43/12 -> 11.65886
A65: Opening Bal (st+lt) | B65: ='PepsiCo-BS'!E23+'PepsiCo-BS'!E27 -> 44978 | C65: =B69 -> 39628 | D65: =C69 -> 36352 | E65: =D69 -> 32521 | F65: =E69 -> 30249
A66: Mandatory Debt (Repay)/Raise | B66: =B10 -> -2118 | C66: =C10 -> -3276 | D66: =D10 -> -3831 | E66: =E10 -> -2272 | F66: =F10 -> -2839
A67: Discretionary Debt Raise | B67: =B46 -> 0 | C67: =C46 -> 0 | D67: =D46 -> 0 | E67: =E46 -> 0 | F67: =F46 -> 0
A68: Discretionary Debt (Repaid) | B68: =(B47)*-1 -> -3232 | C68: =(C47)*-1 -> 0 | D68: =(D47)*-1 -> 0 | E68: =(E47)*-1 -> 0 | F68: =(F47)*-1 -> 0
A69: Total Debt (Short Term + Long Term) | B69: =SUM(B65:B68) -> 39628 | C69: =SUM(C65:C68) -> 36352 | D69: =SUM(D65:D68) -> 32521 | E69: =SUM(E65:E68) -> 30249 | F69: =SUM(F65:F68) -> 27410 | G69: Closing Bal
A72: Short Term Debt | B72: =-C10+B48 -> 3276 | C72: =-D10+C48 -> 3831 | D72: =-E10+D48 -> 2272 | E72: =-F10+E48 -> 2839 | F72: =-G10+F48 -> 20410
A73: Long Term Debt | B73: =B69-B72 -> 36352 | C73: =C69-C72 -> 32521 | D73: =D69-D72 -> 30249 | E73: =E69-E72 -> 27410 | F73: =F69-F72 -> 7000

Sheet Fixed Assets Schedule
A1: PepsiCo Inc.
A2: ='PepsiCo-IS'!A2 -> (in USD million except per Share Data)
A3: Property, Plant & Equipment | B3: ='PepsiCo-IS'!E3 -> 12 | C3: ='PepsiCo-IS'!F3 -> 12 | D3: ='PepsiCo-IS'!G3 -> 12 | E3: ='PepsiCo-IS'!H3 -> 6 | G3: ='PepsiCo-IS'!I3 -> 6 | H3: ='PepsiCo-IS'!K3 -> 12 | I3: ='PepsiCo-IS'!L3 -> 12 | J3: ='PepsiCo-IS'!M3 -> 12 | K3: ='PepsiCo-IS'!N3 -> 12
B4: ='PepsiCo-IS'!E4 -> 43100 | C4: 43465 | D4: 43830 | E4: June-30-2020 | G4: ='PepsiCo-IS'!I4 -> 44196 | H4: ='PepsiCo-IS'!K4 -> 44561 | I4: ='PepsiCo-IS'!L4 -> 44926 | J4: ='PepsiCo-IS'!M4 -> 45291 | K4: ='PepsiCo-IS'!N4 -> 45657
A5: Opening Balance-WDV | B5: 16591 | C5: =B9 -> 17240 | D5: =C9 -> 17589 | E5: =D9 -> 19305 | G5: =E9 -> 19187 | H5: =G9 -> 20303.375 | I5: =H9 -> 19839.788 | J5: =I9 -> 20650.643 | K5: =J9 -> 21506.453
A6: Add: Net Addition during the Period | B6: =B7-B5 -> 2950 | C6: =C7-C5 -> 2679 | D6: =D7-D5 -> 4067 | E6: =E7-E5 -> 966.63076 | G6: =G7-G5 -> 2348.5197 | H6: =H7-H5 -> 2100.0133 | I6: =I7-I5 -> 3479.2286 | J6: =J7-J5 -> 3634.7676 | K6: =K7-K5 -> 3799.3231
A7: Total Depreciable Assets During the Year | B7: =B9+B8 -> 19541 | C7: =C9+C8 -> 19919 | D7: =D9+D8 -> 21656 | E7: =E9+E8 -> 20271.631 | G7: =('PepsiCo-IS'!J6/'Fixed Assets Schedule'!$G$13) -> 21535.52 | H7: =('PepsiCo-IS'!K6/'Fixed Assets Schedule'!$G$13) -> 22403.388 | I7: =('PepsiCo-IS'!L6/'Fixed Assets Schedule'!$G$13) -> 23319.017 | J7: =('PepsiCo-IS'!M6/'Fixed Assets Schedule'!$G$13) -> 24285.411 | K7: =('PepsiCo-IS'!N6/'Fixed Assets Schedule'!$G$13) -> 25305.776
A8: Less: Depreciation during the year | B8: =B20 -> 2301 | C8: =C20 -> 2330 | D8: =D20 -> 2351 | E8: =E20 -> 1084.6308 | G8: =G7*$G$15/2 -> 1232.1451 | H8: =H7*$G$15 -> 2563.5995 | I8: =I7*$G$15 -> 2668.3741 | J8: =J7*$G$15 -> 2778.9577 | K8: =K7*$G$15 -> 2895.7172 | L8: Linked to IS after splitting
A9: Closing Balance-WDV | B9: ='PepsiCo-BS'!B13 -> 17240 | C9: ='PepsiCo-BS'!C13 -> 17589 | D9: ='PepsiCo-BS'!D13 -> 19305 | E9: ='PepsiCo-BS'!E13 -> 19187 | G9: =G7-G8 -> 20303.375 | H9: =H7-H8 -> 19839.788 | I9: =I7-I8 -> 20650.643 | J9: =J7-J8 -> 21506.453 | K9: =K7-K8 -> 22410.059
A10: Source | B10: 10K Dec'17, Pg 84 | C10: 10K Dec'19, Pg 79 | E10: 10Q June'20, Pg 8 | G10: Calculation
E12: 6 Monthly | G12: Yearly
A13: PPE Turnover Ratio | B13: ='PepsiCo-IS'!E6/'Fixed Assets Schedule'!B7 -> 3.2508572 | C13: ='PepsiCo-IS'!F6/'Fixed Assets Schedule'!C7 -> 3.2461971 | D13: ='PepsiCo-IS'!G6/'Fixed Assets Schedule'!D7 -> 3.1012652 | E13: ='PepsiCo-IS'!H6/'Fixed Assets Schedule'!E7 -> 1.4713172 | G13: =AVERAGE(B13:D13) -> 3.1994398
A15: Depreciation Rate | B15: =B8/B7 -> 0.11775242 | C15: =C8/C7 -> 0.11697374 | D15: =D8/D7 -> 0.10856114 | E15: =E8/E7 -> 0.05350486 | G15: =AVERAGE(B15:D15) -> 0.1144291
A18: Depreciation Exp | B18: ='PepsiCo-IS'!E11 -> 2107 | C18: ='PepsiCo-IS'!F11 -> 2144 | D18: ='PepsiCo-IS'!G11 -> 2196 | E18: ='PepsiCo-IS'!H11 -> 1013.1217 | F18: =AVERAGE(B21:E21) -> 0.92600043 | G18: =G20*$F$18 -> 1140.9669 | H18: =H20*$F$18 -> 2373.8943 | I18: =I20*$F$18 -> 2470.9156 | J18: =J20*$F$18 -> 2573.316 | K18: =K20*$F$18 -> 2681.4353 | L18: Splitting
A19: Corporate Depreciation and Amort | B19: ='PepsiCo-IS'!E19 -> 194 | C19: ='PepsiCo-IS'!F19 -> 186 | D19: ='PepsiCo-IS'!G19 -> 155 | E19: ='PepsiCo-IS'!H19 -> 71.509046 | G19: =G20-G18 -> 91.178205 | H19: =H20-H18 -> 189.70526 | I19: =I20-I18 -> 197.45854 | J19: =J20-J18 -> 205.64167 | K19: =K20-K18 -> 214.28182
B20: =SUM(B18:B19) -> 2301 | C20: =SUM(C18:C19) -> 2330 | D20: =SUM(D18:D19) -> 2351 | E20: =SUM(E18:E19) -> 1084.6308 | G20: =G8 -> 1232.1451 | H20: =H8 -> 2563.5995 | I20: =I8 -> 2668.3741 | J20: =J8 -> 2778.9577 | K20: =K8 -> 2895.7172
B21: =B18/B20 -> 0.91568883 | C21: =C18/C20 -> 0.92017167 | D21: =D18/D20 -> 0.93407061 | E21: =E18/E20 -> 0.93407061
A22: Amortizable Intangible Assets, net | B22: =B3 -> 12 | C22: =C3 -> 12 | D22: =D3 -> 12 | E22: =E3 -> 6 | G22: =G3 -> 6 | H22: =H3 -> 12 | I22: =I3 -> 12 | J22: =J3 -> 12 | K22: =K3 -> 12
B23: =B4 -> 43100 | C23: =C4 -> 43465 | D23: =D4 -> 43830 | E23: =E4 -> June-30-2020 | G23: =G4 -> 44196 | H23: =H4 -> 44561 | I23: =I4 -> 44926 | J23: =J4 -> 45291 | K23: =K4 -> 45657
A24: Opening Balance-WDV | B24: 1237 | C24: =B28 -> 1268 | D24: =C28 -> 1644 | E24: =D28 -> 1433 | G24: =E28 -> 1465 | H24: =G28 -> 1429.6742 | I24: =H28 -> 1360.7262 | J24: =I28 -> 1295.1033 | K24: =J28 -> 1232.6452
A25: Add: Net Addition during the Period | B25: =B26-B24 -> 99 | C25: =C26-C24 -> 445 | D25: =D26-D24 -> -130 | E25: =E26-E24 -> 69.369243 | G25: 0 | H25: 0 | I25: 0 | J25: 0 | K25: 0
A26: Total Amortizable Assets During the Year | B26: =B27+B28 -> 1336 | C26: =C27+C28 -> 1713 | D26: =D27+D28 -> 1514 | E26: =E27+E28 -> 1502.3692 | G26: =G24-G25 -> 1465 | H26: =H24-H25 -> 1429.6742 | I26: =I24-I25 -> 1360.7262 | J26: =J24-J25 -> 1295.1033 | K26: =K24-K25 -> 1232.6452
A27: Less: Amortisation during the year | B27: ='PepsiCo-IS'!E20 -> 68 | C27: ='PepsiCo-IS'!F20 -> 69 | D27: ='PepsiCo-IS'!G20 -> 81 | E27: ='PepsiCo-IS'!H20 -> 37.369243 | G27: =G26*$G$32/2 -> 35.325807 | H27: =H26*$G$32 -> 68.94798 | I27: =I26*$G$32 -> 65.62287 | J27: =J26*$G$32 -> 62.458118 | K27: =K26*$G$32 -> 59.44599
A28: Closing Balance-WDV | B28: ='PepsiCo-BS'!B14 -> 1268 | C28: ='PepsiCo-BS'!C14 -> 1644 | D28: ='PepsiCo-BS'!D14 -> 1433 | E28: ='PepsiCo-BS'!E14 -> 1465 | G28: =G26-G27 -> 1429.6742 | H28: =H26-H27 -> 1360.7262 | I28: =I26-I27 -> 1295.1033 | J28: =J26-J27 -> 1232.6452 | K28: =K26-K27 -> 1173.1992
A29: Source | B29: 10K Dec'17, Pg 84 | C29: 10K Dec'19, Pg 79 | E29: 10Q June'20, Pg 8 | G29: Calculation
E31: 6 Monthly
A32: Amortisation Rate | B32: =B27/B26 -> 0.050898204 | C32: =C27/C26 -> 0.04028021 | D32: =D27/D26 -> 0.053500661 | E32: =E27/E26 -> 0.024873541 | G32: =AVERAGE(B32:D32) -> 0.048226358

Sheet PepsiCo-BS
A1: PepsiCo Inc.
A2: ='PepsiCo-IS'!A2 -> (in USD million except per Share Data)
A3: Balance Sheet as of: | B3: ='PepsiCo-IS'!E4 -> 43100 | C3: ='PepsiCo-IS'!F4 -> 43465 | D3: ='PepsiCo-IS'!G4 -> 43830 | E3: ='PepsiCo-IS'!H4 -> 43995 | F3: ='PepsiCo-IS'!J4 -> 44196 | G3: ='PepsiCo-IS'!K4 -> 44561 | H3: ='PepsiCo-IS'!L4 -> 44926 | I3: ='PepsiCo-IS'!M4 -> 45291 | J3: ='PepsiCo-IS'!N4 -> 45657
A4: ASSETS
A5: Cash And Equivalents | B5: 10610 | C5: 8721 | D5: 5509 | E5: 8927 | F5: ='PepsiCo-CFS'!B35 -> 7824.5556 | G5: ='PepsiCo-CFS'!C35 -> 8732.3285 | H5: ='PepsiCo-CFS'!D35 -> 7693.8441 | I5: ='PepsiCo-CFS'!E35 -> 8295.0317 | J5: ='PepsiCo-CFS'!F35 -> 8393.0707
A6: Short Term Investments | B6: 8900 | C6: 272 | D6: 229 | E6: 196 | F6: =E6 -> 196 | G6: =F6 -> 196 | H6: =G6 -> 196 | I6: =H6 -> 196 | J6: =I6 -> 196
A7: Restricted Cash | B7: 0 | C7: 1997 | D7: 0 | E7: 0 | F7: 0 | G7: 0 | H7: 0 | I7: 0 | J7: 0
A8: Accounts and Notes Receivable | B8: 7024 | C8: 7142 | D8: 7822 | E8: 8780 | F8: =F76 -> 7751.2008 | G8: =G76 -> 8063.5694 | H8: =H76 -> 8393.1284 | I8: =I76 -> 8740.9589 | J8: =J76 -> 9108.2153
A9: Inventories | B9: 2947 | C9: 3128 | D9: 3338 | E9: 4314 | F9: =F78 -> 3233.8369 | G9: =G78 -> 3430.3254 | H9: =H78 -> 3570.5232 | I9: =I78 -> 3718.4939 | J9: =J78 -> 3874.7286
A10: Prepaid expenses and other current assets | B10: 1546 | C10: 633 | D10: 747 | E10: 972 | F10: =F80 -> 1039.241 | G10: =G80 -> 1081.1218 | H10: =H80 -> 1125.3073 | I10: =I80 -> 1171.9426 | J10: =J80 -> 1221.1825
A11: Total Current Assets | B11: =SUM(B5:B10) -> 31027 | C11: =SUM(C5:C10) -> 21893 | D11: =SUM(D5:D10) -> 17645 | E11: =SUM(E5:E10) -> 23189 | F11: =SUM(F5:F10) -> 20044.834 | G11: =SUM(G5:G10) -> 21503.345 | H11: =SUM(H5:H10) -> 20978.803 | I11: =SUM(I5:I10) -> 22122.427 | J11: =SUM(J5:J10) -> 22793.197
A13: Net Property, Plant & Equipment | B13: 17240 | C13: 17589 | D13: 19305 | E13: 19187 | F13: ='Fixed Assets Schedule'!G9 -> 20303.375 | G13: ='Fixed Assets Schedule'!H9 -> 19839.788 | H13: ='Fixed Assets Schedule'!I9 -> 20650.643 | I13: ='Fixed Assets Schedule'!J9 -> 21506.453 | J13: ='Fixed Assets Schedule'!K9 -> 22410.059
A14: Amortizable Intangible Assets, net | B14: 1268 | C14: 1644 | D14: 1433 | E14: 1465 | F14: ='Fixed Assets Schedule'!G28 -> 1429.6742 | G14: ='Fixed Assets Schedule'!H28 -> 1360.7262 | H14: ='Fixed Assets Schedule'!I28 -> 1295.1033 | I14: ='Fixed Assets Schedule'!J28 -> 1232.6452 | J14: ='Fixed Assets Schedule'!K28 -> 1173.1992
A15: Goodwill | B15: 14744 | C15: 14808 | D15: 15501 | E15: 17845 | F15: =E15 -> 17845 | G15: =F15 -> 17845 | H15: =G15 -> 17845 | I15: =H15 -> 17845 | J15: =I15 -> 17845
A16: Other indefinite-lived intangible assets | B16: 12570 | C16: 14181 | D16: 14610 | E16: 17530 | F16: =E16 -> 17530 | G16: =F16 -> 17530 | H16: =G16 -> 17530 | I16: =H16 -> 17530 | J16: =I16 -> 17530
A17: Investments in Noncontrolled Affiliates | B17: 2042 | C17: 2409 | D17: 2683 | E17: 2715 | F17: =E17 -> 2715 | G17: =F17 -> 2715 | H17: =G17 -> 2715 | I17: =H17 -> 2715 | J17: =I17 -> 2715
A18: Deferred Income Taxes | B18: 0 | C18: 4364 | D18: 4359 | E18: 4351 | F18: =E18 -> 4351 | G18: =F18 -> 4351 | H18: =G18 -> 4351 | I18: =H18 -> 4351 | J18: =I18 -> 4351
A19: Other Assets | B19: 913 | C19: 760 | D19: 3011 | E19: 3243 | F19: =E19 -> 3243 | G19: =F19 -> 3243 | H19: =G19 -> 3243 | I19: =H19 -> 3243 | J19: =I19 -> 3243
A20: Total Assets | B20: =SUM(B11:B19) -> 79804 | C20: =SUM(C11:C19) -> 77648 | D20: =SUM(D11:D19) -> 78547 | E20: =SUM(E11:E19) -> 89525 | F20: =SUM(F13:F19,F11) -> 87461.883 | G20: =SUM(G13:G19,G11) -> 88387.86 | H20: =SUM(H13:H19,H11) -> 88608.549 | I20: =SUM(I13:I19,I11) -> 90545.525 | J20: =SUM(J13:J19,J11) -> 92060.455
A22: LIABILITIES
A23: Short-term debt obligations | B23: 5485 | C23: 4026 | D23: 2920 | E23: 6607 | F23: ='Debt Schedule'!B72 -> 3276 | G23: ='Debt Schedule'!C72 -> 3831 | H23: ='Debt Schedule'!D72 -> 2272 | I23: ='Debt Schedule'!E72 -> 2839 | J23: ='Debt Schedule'!F72 -> 20410
A24: Accounts payable and other current liabilities | B24: 15017 | C24: 18112 | D24: 17541 | E24: 17220 | F24: =F65 -> 18096.39 | G24: =G65 -> 19021.791 | H24: =H65 -> 19682.08 | I24: =I65 -> 20378.977 | J24: =J65 -> 21114.795
A25: Total Current Liabilities | B25: =SUM(B23:B24) -> 20502 | C25: =SUM(C23:C24) -> 22138 | D25: =SUM(D23:D24) -> 20461 | E25: =SUM(E23:E24) -> 23827 | F25: =SUM(F23:F24) -> 21372.39 | G25: =SUM(G23:G24) -> 22852.791 | H25: =SUM(H23:H24) -> 21954.08 | I25: =SUM(I23:I24) -> 23217.977 | J25: =SUM(J23:J24) -> 41524.795
A27: Long-Term Debt Obligations | B27: 33796 | C27: 28295 | D27: 29148 | E27: 38371 | F27: ='Debt Schedule'!B73 -> 36352 | G27: ='Debt Schedule'!C73 -> 32521 | H27: ='Debt Schedule'!D73 -> 30249 | I27: ='Debt Schedule'!E73 -> 27410 | J27: ='Debt Schedule'!F73 -> 7000
A28: Deferred Income Taxes | B28: 3242 | C28: 3499 | D28: 4091 | E28: 4203 | F28: =E28 -> 4203 | G28: =F28 -> 4203 | H28: =G28 -> 4203 | I28: =H28 -> 4203 | J28: =I28 -> 4203 | K28: Same
A29: Other Liabilities | B29: 11283 | C29: 9114 | D29: 9979 | E29: 10537 | F29: =E29 -> 10537 | G29: =F29 -> 10537 | H29: =G29 -> 10537 | I29: =H29 -> 10537 | J29: =I29 -> 10537 | K29: Same
A30: Total Liabilities | B30: =SUM(B25:B29) -> 68823 | C30: =SUM(C25:C29) -> 63046 | D30: =SUM(D25:D29) -> 63679 | E30: =SUM(E25:E29) -> 76938 | F30: =SUM(F27:F29,F25) -> 72464.39 | G30: =SUM(G27:G29,G25) -> 70113.791 | H30: =SUM(H27:H29,H25) -> 66943.08 | I30: =SUM(I27:I29,I25) -> 65367.977 | J30: =SUM(J27:J29,J25) -> 63264.795
A32: Preferred Stock, no par value | B32: 41
A33: Repurchased Preferred Stock | B33: -197
A35: Common Stock | B35: 24 | C35: 23 | D35: 23 | E35: 23 | F35: =E35 -> 23 | G35: =F35 -> 23 | H35: =G35 -> 23 | I35: =H35 -> 23 | J35: =I35 -> 23 | K35: same
A36: Capital in excess of par value | B36: 3996 | C36: 3953 | D36: 3886 | E36: 3772 | F36: =E36+'PepsiCo-CFS'!B9 -> 3904.1863 | G36: =F36+'PepsiCo-CFS'!C9 -> 4182.0954 | H36: =G36+'PepsiCo-CFS'!D9 -> 4471.3017 | I36: =H36+'PepsiCo-CFS'!E9 -> 4772.4348 | J36: =I36+'PepsiCo-CFS'!F9 -> 5086.1643 | K36: same
A37: Retained Earnings | B37: 52839 | C37: 59947 | D37: 61946 | E37: 62145 | F37: =E37+'PepsiCo-IS'!I46+'PepsiCo-CFS'!B24 -> 64389.262 | G37: =F37+'PepsiCo-IS'!K46+'PepsiCo-CFS'!C24 -> 67335.473 | H37: =G37+'PepsiCo-IS'!L46+'PepsiCo-CFS'!D24 -> 70383.401 | I37: =H37+'PepsiCo-IS'!M46+'PepsiCo-CFS'!E24 -> 73538.178 | J37: =I37+'PepsiCo-IS'!N46+'PepsiCo-CFS'!F24 -> 76784.757
A38: Accumulated other comprehensive loss | B38: -13057 | C38: -15119 | D38: -14300 | E38: -15778 | F38: =E38 -> -15778 | G38: =F38 -> -15778 | H38: =G38 -> -15778 | I38: =H38 -> -15778 | J38: =I38 -> -15778 | K38: same
A39: Repurchased common stock, in excess of par value | B39: -32757 | C39: -34286 | D39: -36769 | E39: -37671 | F39: =E39 -> -37671 | G39: =F39 -> -37671 | H39: =G39 -> -37671 | I39: =H39 -> -37671 | J39: =I39 -> -37671 | K39: same
A40: Total PepsiCo Common Shareholders’ Equity | B40: =SUM(B35:B39) -> 11045 | C40: =SUM(C35:C39) -> 14518 | D40: =SUM(D35:D39) -> 14786 | E40: =SUM(E35:E39) -> 12491 | F40: =SUM(F35:F39) -> 14867.449 | G40: =SUM(G35:G39) -> 18091.569 | H40: =SUM(H35:H39) -> 21428.703 | I40: =SUM(I35:I39) -> 24884.613 | J40: =SUM(J35:J39) -> 28444.921
A41: Noncontrolling interests | B41: 92 | C41: 84 | D41: 82 | E41: 96 | F41: =E41+'PepsiCo-IS'!I44 -> 130.04454 | G41: =F41+'PepsiCo-IS'!K44 -> 182.50007 | H41: =G41+'PepsiCo-IS'!L44 -> 236.76661 | I41: =H41+'PepsiCo-IS'!M44 -> 292.93554 | J41: =I41+'PepsiCo-IS'!N44 -> 350.73895
A42: Total Equity | B42: =B40+B41 -> 11137 | C42: =C40+C41 -> 14602 | D42: =D40+D41 -> 14868 | E42: =E40+E41 -> 12587 | F42: =SUM(F40:F41) -> 14997.493 | G42: =SUM(G40:G41) -> 18274.069 | H42: =SUM(H40:H41) -> 21665.469 | I42: =SUM(I40:I41) -> 25177.548 | J42: =SUM(J40:J41) -> 28795.66
A44: Total Liabilities And Equity | B44: =B30+B32+B33+B42 -> 79804 | C44: =C30+C42 -> 77648 | D44: =D30+D42 -> 78547 | E44: =E30+E42 -> 89525 | F44: =F42+F30 -> 87461.883 | G44: =G42+G30 -> 88387.86 | H44: =H42+H30 -> 88608.549 | I44: =I42+I30 -> 90545.525 | J44: =J42+J30 -> 92060.455
A45: Check | B45: =B20-B44 -> 0 | C45: =C20-C44 -> 0 | D45: =D20-D44 -> 0 | E45: =E20-E44 -> 0 | F45: =F20-F44 -> 0 | G45: =G20-G44 -> 0 | H45: =H20-H44 -> 0 | I45: =I20-I44 -> 0 | J45: =J20-J44 -> 0
A46: Source | B46: 10K Dec'18, Pg 83 | C46: 10K Dec'19, Pg 89 | D46: 10K Dec'19, Pg 89 | E46: 10Q June'20, Pg 8
A48: Other Assets | B48: =B19 -> 913 | C48: =C19 -> 760 | D48: =D19 -> 3011 | E48: =E19 -> 3243
A49: Notes and Accounts Receivable-Non Current | B49: 59 | C49: 86 | D49: 85 | E49: No Breakup Available in Quarterly Filing
A50: Deferred marketplace spending | B50: 134 | C50: 112 | D50: 147
A51: Overfunded Plan Assets | B51: 374 | C51: 269 | D51: 846
A52: Right-of-use assets | B52: 0 | C52: 0 | D52: 1548
A53: Other | B53: 346 | C53: 293 | D53: 385
B54: =SUM(B49:B53) -> 913 | C54: =SUM(C49:C53) -> 760 | D54: =SUM(D49:D53) -> 3011 | E54: =SUM(E49:E53) -> 0
A55: Source
A57: Other Liabilities | B57: =B29 -> 11283 | C57: =C29 -> 9114 | D57: =D29 -> 9979 | E57: =E29 -> 10537
A58: Reserve for Income Taxes | B58: 2200 | C58: 1400 | D58: 1400 | E58: No Breakup Available in Quarterly Filing
A59: Accrue interest related to reserves for income taxes | B59: 283 | C59: 179 | D59: 250
A60: Unfunded Pension and Other Benefit Liabilities-Non Current | B60: =2407+114+791 -> 3312 | C60: =1627+88+670 -> 2385 | D60: =1620+119+628 -> 2367
A61: Operating Lease Liab-Non Current | B61: 0 | C61: 0 | D61: 1118
A62: Other-Balance | B62: =B57-SUM(B58:B61) -> 5488 | C62: =C57-SUM(C58:C61) -> 5150 | D62: =D57-SUM(D58:D61) -> 4844
A65: Accounts payable and other current liabilities | B65: =B24 -> 15017 | C65: =C24 -> 18112 | D65: =D24 -> 17541 | E65: =E24 -> 17220 | F65: =F70+F71 -> 18096.39 | G65: =G70+G71 -> 19021.791 | H65: =H70+H71 -> 19682.08 | I65: =I70+I71 -> 20378.977 | J65: =J70+J71 -> 21114.795
A66: Less: Non Operating Items
A67: Dividends payable | B67: 1161 | C67: 1329 | D67: 1351 | E67: No Break Up Available
A68: SodaStream consideration payable | B68: 0 | C68: 1997 | D68: 58
A69: Current lease liabilities | B69: 0 | C69: 0 | D69: 442
A70: Accounts payable and other current liabilities-OPERATING | B70: =B65-SUM(B67:B69) -> 13856 | C70: =C65-SUM(C67:C69) -> 14786 | D70: =D65-SUM(D67:D69) -> 15690 | E70: =D70-1336 -> 14354 | F70: =F84 -> 15230.39 | G70: =G84 -> 16155.791 | H70: =H84 -> 16816.08 | I70: =I84 -> 17512.977 | J70: =J84 -> 18248.795 | K70: operating
A71: Accounts payable and other current liabilities-NON OPERATING | B71: =B65-B70 -> 1161 | C71: =C65-C70 -> 3326 | D71: =D65-D70 -> 1851 | E71: =E65-E70 -> 2866 | F71: =E71 -> 2866 | G71: =F71 -> 2866 | H71: =G71 -> 2866 | I71: =H71 -> 2866 | J71: =I71 -> 2866 | K71: non operating | L71: Assumed to be constant
A72: Source | B72: 10K Dec'18, Pg 127 | C72: 10K Dec'19, Pg 125 | D72: 10K Dec'19, Pg 125 | E72: 10Q June'20, Pg 6
A74: Working Capital
A75: Operating Current Assets
A76: =A8 -> Accounts and Notes Receivable | B76: =B8 -> 7024 | C76: =C8 -> 7142 | D76: =D8 -> 7822 | E76: =E8 -> 8780 | F76: =$F$77/365*'PepsiCo-IS'!J6 -> 7751.2008 | G76: =$F$77/365*'PepsiCo-IS'!K6 -> 8063.5694 | H76: =$F$77/365*'PepsiCo-IS'!L6 -> 8393.1284 | I76: =$F$77/365*'PepsiCo-IS'!M6 -> 8740.9589 | J76: =$F$77/365*'PepsiCo-IS'!N6 -> 9108.2153
A77: Receivable Turnover Ratio | B77: =365/('PepsiCo-IS'!E6/'PepsiCo-BS'!B76) -> 40.358284 | C77: =365/('PepsiCo-IS'!F6/'PepsiCo-BS'!C76) -> 40.315337 | D77: =365/('PepsiCo-IS'!G6/'PepsiCo-BS'!D76) -> 42.510237 | E77: Don’t apply on 6m | F77: =AVERAGE(B77:D77) -> 41.061286 | G77: DAYS SALES OUTSTANDING (SALES)
A78: =A9 -> Inventories | B78: =B9 -> 2947 | C78: =C9 -> 3128 | D78: =D9 -> 3338 | E78: =E9 -> 4314 | F78: =$F$79/365*'PepsiCo-IS'!J10 -> 3233.8369 | G78: =$F$79/365*'PepsiCo-IS'!K10 -> 3430.3254 | H78: =$F$79/365*'PepsiCo-IS'!L10 -> 3570.5232 | I78: =$F$79/365*'PepsiCo-IS'!M10 -> 3718.4939 | J78: =$F$79/365*'PepsiCo-IS'!N10 -> 3874.7286
A79: Inventory Turnover Ratio | B79: =365*B78/'PepsiCo-IS'!E10 -> 40.291231 | C79: =365*C78/'PepsiCo-IS'!F10 -> 42.050753 | D79: =365*D78/'PepsiCo-IS'!G10 -> 43.757003 | E79: Don’t apply on 6m | F79: =AVERAGE(B79:D79) -> 42.032996 | G79: DAYS INVENTORY OUTSTANDING (COGS w/o depr)
A80: =A10 -> Prepaid expenses and other current assets | B80: =B10 -> 1546 | C80: =C10 -> 633 | D80: =D10 -> 747 | E80: =E10 -> 972 | F80: =$F$81*'PepsiCo-IS'!J6 -> 1039.241 | G80: =$F$81*'PepsiCo-IS'!K6 -> 1081.1218 | H80: =$F$81*'PepsiCo-IS'!L6 -> 1125.3073 | I80: =$F$81*'PepsiCo-IS'!M6 -> 1171.9426 | J80: =$F$81*'PepsiCo-IS'!N6 -> 1221.1825
A81: %age of Sales | B81: =B80/'PepsiCo-IS'!E6 -> 0.024336875 | C81: =C80/'PepsiCo-IS'!F6 -> 0.0097895176 | D81: =D80/'PepsiCo-IS'!G6 -> 0.011122526 | F81: =AVERAGE(B81:D81) -> 0.015082973
A83: Operating Current Liabilities
A84: =A70 -> Accounts payable and other current liabilities-OPERATING | B84: =B70 -> 13856 | C84: =C70 -> 14786 | D84: =D70 -> 15690 | E84: =E70 -> 14354 | F84: =$F$85/365*'PepsiCo-IS'!J10 -> 15230.39 | G84: =$F$85/365*'PepsiCo-IS'!K10 -> 16155.791 | H84: =$F$85/365*'PepsiCo-IS'!L10 -> 16816.08 | I84: =$F$85/365*'PepsiCo-IS'!M10 -> 17512.977 | J84: =$F$85/365*'PepsiCo-IS'!N10 -> 18248.795 | K84: only operating part will be taken here since will be used in CFO and CFO only takes operating
A85: Payable Turnover Ratio | B85: =365*B84/'PepsiCo-IS'!E10 -> 189.43851 | C85: =365*C84/'PepsiCo-IS'!F10 -> 198.77316 | D85: =365*D84/'PepsiCo-IS'!G10 -> 205.67627 | F85: =AVERAGE(B85:D85) -> 197.96265 | G85: DAYS PAYABLE OUTSTANDING (COGS w/o depr)

Sheet PepsiCo-CFS
A1: PepsiCo Inc.
A2: ='PepsiCo-IS'!A2 -> (in USD million except per Share Data)
A3: Cash Flow Statement | B3: ='PepsiCo-IS'!I3 -> 6 | C3: ='PepsiCo-IS'!K3 -> 12 | D3: ='PepsiCo-IS'!L3 -> 12 | E3: ='PepsiCo-IS'!M3 -> 12 | F3: ='PepsiCo-IS'!N3 -> 12
B4: ='PepsiCo-IS'!I4 -> 44196 | C4: ='PepsiCo-IS'!K4 -> 44561 | D4: ='PepsiCo-IS'!L4 -> 44926 | E4: ='PepsiCo-IS'!M4 -> 45291 | F4: ='PepsiCo-IS'!N4 -> 45657
A6: Cash From Operating Activities
A7: Net Income | B7: ='PepsiCo-IS'!I40 -> 4578.3103 | C7: ='PepsiCo-IS'!K40 -> 8278.7222 | D7: ='PepsiCo-IS'!L40 -> 8564.5422 | E7: ='PepsiCo-IS'!M40 -> 8864.7838 | F7: ='PepsiCo-IS'!N40 -> 9122.7442 | G7: Since it’s a consolidated Statement Net income BEFORE distribution to minority
A8: Depreciation and amortization | B8: ='PepsiCo-IS'!I11+'PepsiCo-IS'!I19+'PepsiCo-IS'!I20 -> 1267.4709 | C8: ='PepsiCo-IS'!K11+'PepsiCo-IS'!K19+'PepsiCo-IS'!K20 -> 2632.5475 | D8: ='PepsiCo-IS'!L11+'PepsiCo-IS'!L19+'PepsiCo-IS'!L20 -> 2733.997 | E8: ='PepsiCo-IS'!M11+'PepsiCo-IS'!M19+'PepsiCo-IS'!M20 -> 2841.4158 | F8: ='PepsiCo-IS'!N11+'PepsiCo-IS'!N19+'PepsiCo-IS'!N20 -> 2955.1632
A9: Share-based compensation expense | B9: ='PepsiCo-IS'!I72 -> 132.18635 | C9: ='PepsiCo-IS'!K72 -> 277.90909 | D9: ='PepsiCo-IS'!L72 -> 289.20624 | E9: ='PepsiCo-IS'!M72 -> 301.13316 | F9: ='PepsiCo-IS'!N72 -> 313.72945
A10: Change in assets and liabilities:
A11: Accounts and notes receivable | B11: ='PepsiCo-BS'!E8-'PepsiCo-BS'!F8 -> 1028.7992 | C11: ='PepsiCo-BS'!F8-'PepsiCo-BS'!G8 -> -312.36864 | D11: ='PepsiCo-BS'!G8-'PepsiCo-BS'!H8 -> -329.55902 | E11: ='PepsiCo-BS'!H8-'PepsiCo-BS'!I8 -> -347.83047 | F11: ='PepsiCo-BS'!I8-'PepsiCo-BS'!J8 -> -367.2564
A12: Inventories | B12: ='PepsiCo-BS'!E9-'PepsiCo-BS'!F9 -> 1080.1631 | C12: ='PepsiCo-BS'!F9-'PepsiCo-BS'!G9 -> -196.48852 | D12: ='PepsiCo-BS'!G9-'PepsiCo-BS'!H9 -> -140.1978 | E12: ='PepsiCo-BS'!H9-'PepsiCo-BS'!I9 -> -147.97066 | F12: ='PepsiCo-BS'!I9-'PepsiCo-BS'!J9 -> -156.23465
A13: Prepaid expenses and other current assets | B13: ='PepsiCo-BS'!E10-'PepsiCo-BS'!F10 -> -67.240976 | C13: ='PepsiCo-BS'!F10-'PepsiCo-BS'!G10 -> -41.880774 | D13: ='PepsiCo-BS'!G10-'PepsiCo-BS'!H10 -> -44.185571 | E13: ='PepsiCo-BS'!H10-'PepsiCo-BS'!I10 -> -46.635314 | F13: ='PepsiCo-BS'!I10-'PepsiCo-BS'!J10 -> -49.239841
A14: Accounts payable and other current liabilities | B14: ='PepsiCo-BS'!F70-'PepsiCo-BS'!E70 -> 876.38988 | C14: ='PepsiCo-BS'!G70-'PepsiCo-BS'!F70 -> 925.40127 | D14: ='PepsiCo-BS'!H70-'PepsiCo-BS'!G70 -> 660.28906 | E14: ='PepsiCo-BS'!I70-'PepsiCo-BS'!H70 -> 696.8969 | F14: ='PepsiCo-BS'!J70-'PepsiCo-BS'!I70 -> 735.81776 | G14: Biforcated into two parts operating/non operating and ONLY OPERATING USED
A16: Net Cash Provided by Operating Activities | B16: =SUM(B7:B14) -> 8896.0787 | C16: =SUM(C7:C14) -> 11563.842 | D16: =SUM(D7:D14) -> 11734.092 | E16: =SUM(E7:E14) -> 12161.793 | F16: =SUM(F7:F14) -> 12554.724
A18: Cash From Investing Activities
A19: Capital Expenditure | B19: =-'Fixed Assets Schedule'!G6-'Fixed Assets Schedule'!G25 -> -2348.5197 | C19: =-'Fixed Assets Schedule'!H6-'Fixed Assets Schedule'!H25 -> -2100.0133 | D19: =-'Fixed Assets Schedule'!I6-'Fixed Assets Schedule'!I25 -> -3479.2286 | E19: =-'Fixed Assets Schedule'!J6-'Fixed Assets Schedule'!J25 -> -3634.7676 | F19: =-'Fixed Assets Schedule'!K6-'Fixed Assets Schedule'!K25 -> -3799.3231
A21: Net Cash Used for Investing Activities | B21: =B19 -> -2348.5197 | C21: =C19 -> -2100.0133 | D21: =D19 -> -3479.2286 | E21: =E19 -> -3634.7676 | F21: =F19 -> -3799.3231
A23: Cash From Financing Activities
A24: Cash dividends paid | B24: =-'PepsiCo-IS'!I76*'PepsiCo-IS'!I48 -> -2300.0034 | C24: =-'PepsiCo-IS'!K48*'PepsiCo-IS'!K76 -> -5280.0559 | D24: =-'PepsiCo-IS'!L48*'PepsiCo-IS'!L76 -> -5462.3479 | E24: =-'PepsiCo-IS'!M48*'PepsiCo-IS'!M76 -> -5653.838 | F24: =-'PepsiCo-IS'!N48*'PepsiCo-IS'!N76 -> -5818.3615
A25: Cash before Raising (Repayment) of Debt | B25: =B16+B21+B24 -> 4247.5556 | C25: =C16+C21+C24 -> 4183.773 | D25: =D16+D21+D24 -> 2792.5156 | E25: =E16+E21+E24 -> 2873.1876 | F25: =F16+F21+F24 -> 2937.039 | G25: ALL INCLUDED HERE CFO CFI CFF just Debt not included
A27: Debt Raised | B27: ='Debt Schedule'!B46 -> 0 | C27: ='Debt Schedule'!C46 -> 0 | D27: ='Debt Schedule'!D46 -> 0 | E27: ='Debt Schedule'!E46 -> 0 | F27: ='Debt Schedule'!F46 -> 0
A28: Debt Repaid | B28: ='Debt Schedule'!B10-'Debt Schedule'!B47 -> -5350 | C28: ='Debt Schedule'!C10-'Debt Schedule'!C47 -> -3276 | D28: ='Debt Schedule'!D10-'Debt Schedule'!D47 -> -3831 | E28: ='Debt Schedule'!E10-'Debt Schedule'!E47 -> -2272 | F28: ='Debt Schedule'!F10-'Debt Schedule'!F47 -> -2839
A31: Net Cash Provided by/(Used for) Financing Activities | B31: =B24+B27+B28 -> -7650.0034 | C31: =C24+C27+C28 -> -8556.0559 | D31: =D24+D27+D28 -> -9293.3479 | E31: =E24+E27+E28 -> -7925.838 | F31: =F24+F27+F28 -> -8657.3615
A33: Net Increase/(Decrease) in Cash and Cash Equivalents | B33: =B16+B21+B31 -> -1102.4444 | C33: =C16+C21+C31 -> 907.77296 | D33: =D16+D21+D31 -> -1038.4844 | E33: =E16+E21+E31 -> 601.18763 | F33: =F16+F21+F31 -> 98.039004
A34: Cash and Cash Equivalents, Beginning of Year | B34: ='PepsiCo-BS'!E5 -> 8927 | C34: ='PepsiCo-BS'!F5 -> 7824.5556 | D34: ='PepsiCo-BS'!G5 -> 8732.3285 | E34: ='PepsiCo-BS'!H5 -> 7693.8441 | F34: ='PepsiCo-BS'!I5 -> 8295.0317
A35: Cash and Cash Equivalents, End of Period | B35: =B33+B34 -> 7824.5556 | C35: =C33+C34 -> 8732.3285 | D35: =D33+D34 -> 7693.8441 | E35: =E33+E34 -> 8295.0317 | F35: =F33+F34 -> 8393.0707
A37: Source: Calculations

Sheet PepsiCo-IS
A1: PepsiCo Inc.
A2: (in USD million except per Share Data) | J2: SUM OF COL I and H
A3: Income Statement | E3: 12 | F3: 12 | G3: 12 | H3: 6 | I3: 6 | J3: 12 | K3: 12 | L3: 12 | M3: 12 | N3: 12
E4: 43100 | F4: 43465 | G4: 43830 | H4: 43995 | I4: 44196 | J4: 44196 | K4: 44561 | L4: 44926 | M4: 45291 | N4: 45657
A6: Net Revenue | D6: ='Revenue Segments'!B48 -> 62799 | E6: ='Revenue Segments'!C48 -> 63525 | F6: ='Revenue Segments'!D48 -> 64661 | G6: ='Revenue Segments'!E48 -> 67161 | H6: ='Revenue Segments'!H48 -> 29826 | I6: ='Revenue Segments'!K48 -> 39075.6 | J6: ='Revenue Segments'!M48 -> 68901.6 | K6: ='Revenue Segments'!N48 -> 71678.292 | L6: ='Revenue Segments'!O48 -> 74607.792 | M6: ='Revenue Segments'!P48 -> 77699.71 | N6: ='Revenue Segments'!Q48 -> 80964.308 | O6: From Revenue Segment
A7: Cost of Sales-Reported | E7: =28796 -> 28796 | F7: 29381 | G7: 30132 | H7: 13215
A8: Impact of Special Items | E8: 8 | F8: =-83-3 -> -86 | G8: =57-115-34 -> -92 | H8: =-24-3-19 -> -46
A9: Cost of Sales-Normalised | E9: =E7+E8 -> 28804 | F9: =F7+F8 -> 29295 | G9: =G7+G8 -> 30040 | H9: =H7+H8 -> 13169 | I9: =I10+I11 -> 17066.61 | J9: =H9+I9 -> 30235.61 | K9: =SUM(K10:K11) -> 32161.654 | L9: =SUM(L10:L11) -> 33476.105 | M9: =SUM(M10:M11) -> 34863.431 | N9: =SUM(N10:N11) -> 36328.238
A10: Cost of Sales (Other than Depreciation Exp) | E10: =E9-E11 -> 26697 | F10: =F9-F11 -> 27151 | G10: =G9-G11 -> 27844 | H10: =H9-H11 -> 12155.878 | I10: =I6*$I$63 -> 15925.643 | J10: =H10+I10 -> 28081.521 | K10: =K6*$K$63 -> 29787.76 | L10: =L6*$K$63 -> 31005.189 | M10: =M6*$K$63 -> 32290.115 | N10: =N6*$K$63 -> 33646.803
A11: Depreciation Exp | E11: 2107 | F11: 2144 | G11: 2196 | H11: =1122*G11/($G$11+$G$19+$G$20) -> 1013.1217 | I11: ='Fixed Assets Schedule'!G18 -> 1140.9669 | J11: =H11+I11 -> 2154.0886 | K11: ='Fixed Assets Schedule'!H18 -> 2373.8943 | L11: ='Fixed Assets Schedule'!I18 -> 2470.9156 | M11: ='Fixed Assets Schedule'!J18 -> 2573.316 | N11: ='Fixed Assets Schedule'!K18 -> 2681.4353 | O11: from FA Schedule
A13: Gross Profit-Normalised | C13: =C6-C9 -> 0 | D13: =D6-D9 -> 62799 | E13: =E6-E9 -> 34721 | F13: =F6-F9 -> 35366 | G13: =G6-G9 -> 37121 | H13: =H6-H9 -> 16657 | I13: =I6-I9 -> 22008.99 | J13: =SUM(H13:I13) -> 38665.99 | K13: =K6-K9 -> 39516.638 | L13: =L6-L9 -> 41131.687 | M13: =M6-M9 -> 42836.279 | N13: =N6-N9 -> 44636.07
A15: Selling, General & Admin Exp.-Reported | E15: 24453 | F15: 25170 | G15: 26738 | H15: 12368
A16: Impact of Special Items | E16: =7-229 -> -222 | F16: =-80-269-75 -> -424 | G16: =55-253-21 -> -219 | H16: =-73-53-224 -> -350
A17: Selling, General & Admin Exp.-Normalised | E17: =E15+E16 -> 24231 | F17: =F15+F16 -> 24746 | G17: =G15+G16 -> 26519 | H17: =H15+H16 -> 12018 | I17: =SUM(I18:I20) -> 15728.867 | J17: =H17+I17 -> 27746.867 | K17: =SUM(K18:K20) -> 27974.96 | L17: =SUM(L18:L20) -> 29112.157 | M17: =SUM(M18:M20) -> 30312.748 | N17: =SUM(N18:N20) -> 31580.719
A18: Selling, General & Admin Exp. (Excluding Amortisation Exp) | E18: =E17-E20-E19 -> 23969 | F18: =F17-F20-F19 -> 24491 | G18: =G17-G20-G19 -> 26283 | H18: =H17-H20-H19 -> 11909.122 | I18: =$I$64*I6 -> 15602.363 | J18: =H18+I18 -> 27511.484 | K18: =K6*$K$64 -> 27716.307 | L18: =L6*$K$64 -> 28849.076 | M18: =M6*$K$64 -> 30044.648 | N18: =N6*$K$64 -> 31306.991
A19: Corporate Depreciation and Amort | E19: 194 | F19: 186 | G19: 155 | H19: =1122*G19/($G$11+$G$19+$G$20) -> 71.509046 | I19: ='Fixed Assets Schedule'!G19 -> 91.178205 | J19: =H19+I19 -> 162.68725 | K19: ='Fixed Assets Schedule'!H19 -> 189.70526 | L19: ='Fixed Assets Schedule'!I19 -> 197.45854 | M19: ='Fixed Assets Schedule'!J19 -> 205.64167 | N19: ='Fixed Assets Schedule'!K19 -> 214.28182 | O19: from FA Schedule
A20: Amortisation of Intangible Assets | E20: 68 | F20: 69 | G20: 81 | H20: =1122*G20/($G$11+$G$19+$G$20) -> 37.369243 | I20: ='Fixed Assets Schedule'!G27 -> 35.325807 | J20: =H20+I20 -> 72.695051 | K20: ='Fixed Assets Schedule'!H27 -> 68.94798 | L20: ='Fixed Assets Schedule'!I27 -> 65.62287 | M20: ='Fixed Assets Schedule'!J27 -> 62.458118 | N20: ='Fixed Assets Schedule'!K27 -> 59.44599 | O20: from FA Schedule
A22: Operating Income / EBIT-Normalised | E22: =E13-E17 -> 10490 | F22: =F13-F17 -> 10620 | G22: =G13-G17 -> 10602 | H22: =H13-H17 -> 4639 | I22: =I13-I17 -> 6280.1228 | J22: =H22+I22 -> 10919.123 | K22: =K13-K17 -> 11541.677 | L22: =L13-L17 -> 12019.53 | M22: =M13-M17 -> 12523.531 | N22: =N13-N17 -> 13055.351
A24: Other pension and retiree medical benefits (expense)/income-Reported | E24: 233 | F24: 298 | G24: -44 | H24: 161
A25: Impact of Special Items | E25: 66 | F25: 36 | G25: =2+273 -> 275 | H25: 7
A26: Other pension and retiree medical benefits (expense)/income-Normalised | E26: =E24+E25 -> 299 | F26: =F24+F25 -> 334 | G26: =G24+G25 -> 231 | H26: =H24+H25 -> 168 | I26: =I6*$I$66 -> 220.09994 | J26: =H26+I26 -> 388.09994 | K26: =K6*$K$66 -> 339.47511 | L26: =L6*$K$66 -> 353.3495 | M26: =M6*$K$66 -> 367.99311 | N26: =N6*$K$66 -> 383.45455
A28: Interest Expense-Reported | E28: -1151 | F28: -1525 | G28: -1135
A29: Impact of Special Items | E29: 0 | F29: 253 | G29: 0
A30: Interest Expense-Normalised | E30: =E28+E29 -> -1151 | F30: =F28+F29 -> -1272 | G30: =G28+G29 -> -1135 | H30: -525 | I30: =-('Debt Schedule'!M35+'Debt Schedule'!B52) -> -674.03418 | J30: =I30+H30 -> -1199.0342 | K30: =-SUM('Debt Schedule'!C52,'Debt Schedule'!N35) -> -1192.749 | L30: =-SUM('Debt Schedule'!D52,'Debt Schedule'!O35) -> -1102.659 | M30: =-SUM('Debt Schedule'!E52,'Debt Schedule'!P35) -> -997.3065 | N30: =-SUM('Debt Schedule'!F52,'Debt Schedule'!Q35) -> -953.5545 | O30: From Debt Schedule
A32: Interest Income and Other | E32: 244 | F32: 306 | G32: 200 | I32: ='Debt Schedule'!B61 -> 4.9609152 | J32: =I32+H32 -> 4.9609152 | K32: ='Debt Schedule'!C61 -> 10.321674 | L32: ='Debt Schedule'!D61 -> 10.743522 | M32: ='Debt Schedule'!E61 -> 11.188758 | N32: ='Debt Schedule'!F61 -> 11.65886 | O32: From Debt Schedule
A34: Income before Income Taxes-Normalised | B34: =B22+B26+B28+B32 -> 0 | C34: =C22+C26+C28+C32 -> 0 | D34: =D22+D26+D28+D32 -> 0 | E34: =E22+E26+E30+E32 -> 9882 | F34: =F22+F26+F30+F32 -> 9988 | G34: =G22+G26+G30+G32 -> 9898 | H34: =H22+H26+H30+H32 -> 4282 | I34: =I22+I26+I30+I32 -> 5831.1495 | J34: =I34+H34 -> 10113.149 | K34: =K22+K26+K30+K32 -> 10698.725 | L34: =L22+L26+L30+L32 -> 11280.964 | M34: =M22+M26+M30+M32 -> 11905.407 | N34: =N22+N26+N30+N32 -> 12496.91
A36: Income Tax Expense-Reported | E36: 4694 | F36: -3370 | G36: 1959 | H36: 870
A37: Impact of Special Items | E37: =-7+71-2451 -> -2387 | F37: =38+56+28+5064+62 -> 5248 | G37: =-25+67+8+62+8 -> 120 | H37: =24+10+16 -> 50
A38: Income Tax Expense-Normalised | E38: =E36+E37 -> 2307 | F38: =F36+F37 -> 1878 | G38: =G36+G37 -> 2079 | H38: =H36+H37 -> 920 | I38: =I34*$I$68 -> 1252.8392 | J38: =H38+I38 -> 2172.8392 | K38: =K34*K68 -> 2420.0029 | L38: =L34*L68 -> 2716.4219 | M38: =M34*M68 -> 3040.6228 | N38: =N34*N68 -> 3374.1656
A40: Net Income-Normalised | E40: =E34-E38 -> 7575 | F40: =F34-F38 -> 8110 | G40: =G34-G38 -> 7819 | H40: =H34-H38 -> 3362 | I40: =I34-I38 -> 4578.3103 | J40: =H40+I40 -> 7940.3103 | K40: =K34-K38 -> 8278.7222 | L40: =L34-L38 -> 8564.5422 | M40: =M34-M38 -> 8864.7838 | N40: =N34-N38 -> 9122.7442
A42: Share of noncontrolling interests-Reported | E42: 51 | F42: 44 | G42: 39 | H42: 25
A43: Impact of Special Items | E43: 0 | F43: 1 | G43: 5 | H43: 0
A44: Share of noncontrolling interests-Normalised | E44: =E42+E43 -> 51 | F44: =F42+F43 -> 45 | G44: =G42+G43 -> 44 | H44: =H42+H43 -> 25 | I44: =I40*$I$70 -> 34.044544 | J44: =H44+I44 -> 59.044544 | K44: =K40*$K$70 -> 52.455529 | L44: =L40*$K$70 -> 54.266538 | M44: =M40*$K$70 -> 56.168925 | N44: =N40*$K$70 -> 57.80341
A46: Net Income attributable to PepsiCo-Normalised | E46: =E40-E44 -> 7524 | F46: =F40-F44 -> 8065 | G46: =G40-G44 -> 7775 | H46: =H40-H44 -> 3337 | I46: =I40-I44 -> 4544.2657 | J46: =H46+I46 -> 7881.2657 | K46: =K40-K44 -> 8226.2667 | L46: =L40-L44 -> 8510.2756 | M46: =M40-M44 -> 8808.6149 | N46: =N40-N44 -> 9064.9408
A48: Weighted Average Common Shares Outstanding-Diluted | E48: 1438 | F48: 1425 | G48: 1407 | H48: 1395 | I48: =H48 -> 1395 | J48: =I48 -> 1395 | K48: =J48 -> 1395 | L48: =K48 -> 1395 | M48: =L48 -> 1395 | N48: =M48 -> 1395
A50: Earning Per Share-Diluted | E50: =E46/E48 -> 5.232267 | F50: =F46/F48 -> 5.6596491 | G50: =G46/G48 -> 5.5259417 | H50: =H46/H48 -> 2.3921147 | I50: =I46/I48 -> 3.2575382 | J50: =J46/J48 -> 5.6496529 | K50: =K46/K48 -> 5.8969654 | L50: =L46/L48 -> 6.100556 | ... N50: =N46/N48 -> 6.4981654
A52: Source | E52: 10K Dec'19, Pg 75, 61 and 62 | H52: 10Q June'20, Pg 4 and 46 | I52: Calculation
A55: Profitability ratios
A56: Sales growth (%) | E56: =E6/D6-1 -> 0.011560694 | F56: =F6/E6-1 -> 0.017882723 | G56: =G6/F6-1 -> 0.038663182
A57: Gross profit margins (%)-Normalised | E57: =E13/E6 -> 0.54657222 | F57: =F13/F6 -> 0.54694484 | G57: =G13/G6 -> 0.55271661 | H57: =H13/H6 -> 0.55847247
A58: EBITDA margins (%)-Normalised | E58: =(E22+E11+E19+E20)/E6 -> 0.20242424 | F58: =(F22+F11+F19+F20)/F6 -> 0.20134239 | G58: =(G22+G11+G19+G20)/G6 -> 0.19407096 | H58: =(H22+H11+H19+H20)/H6 -> 0.19315362
A59: EBIT margins (%)-Normalised | E59: =E22/E6 -> 0.16513184 | F59: =F22/F6 -> 0.1642412 | G59: =G22/G6 -> 0.15785947 | H59: =H22/H6 -> 0.15553544
A60: Net Income margins (%)-Normalised | E60: =E40/E6 -> 0.11924439 | F60: =F40/F6 -> 0.12542336 | G60: =G40/G6 -> 0.11642173 | H60: =H40/H6 -> 0.11272045
A62: Cost as % of sales | K62: FOR 20-24 MONTHS
A63: Cost of Sales (Other than Depreciation Exp) | E63: =E10/E6 -> 0.42025974 | F63: =F10/F6 -> 0.41989762 | G63: =G10/G6 -> 0.41458585 | H63: =H10/H6 -> 0.40755979 | I63: =H63 -> 0.40755979 | K63: =AVERAGE(E63:H63) -> 0.41557575
A64: Selling, General & Admin Exp. (Excluding Amortisation Exp) | E64: =E18/E6 -> 0.37731602 | F64: =F18/F6 -> 0.37875999 | G64: =G18/G6 -> 0.39134319 | H64: =H18/H6 -> 0.39928659 | I64: =H64 -> 0.39928659 | K64: =AVERAGE(E64:H64) -> 0.38667645
A66: Other pension and retiree medical benefits (expense)/income | E66: =E26/E6 -> 0.0047068083 | F66: =F26/F6 -> 0.0051654011 | G66: =G26/G6 -> 0.0034394961 | H66: =H26/H6 -> 0.0056326695 | I66: =H66 -> 0.0056326695 | K66: =AVERAGE(E66:H66) -> 0.0047360938 | O66: Increment | P66: =(O68-P68)/4 -> 0.014601519
A68: Tax Rate-Normalised (%age of PBT) | E68: =E38/E34 -> 0.23345477 | F68: =F38/F34 -> 0.18802563 | G68: =G38/G34 -> 0.21004243 | H68: =H38/H34 -> 0.21485287 | I68: =H68 -> 0.21485287 | K68: =AVERAGE(E68:H68)+P66 -> 0.22619544 | L68: =K68+$P$66 -> 0.24079696 | M68: =L68+$P$66 -> 0.25539848 | N68: =M68+$P$66 -> 0.27 | O68: 0.27 | P68: 0.21159393
A70: Share of noncontrolling interests (%age of Net Income) | E70: =E44/E40 -> 0.0067326733 | F70: =F44/F40 -> 0.0055487053 | G70: =G44/G40 -> 0.0056273181 | H70: =H44/H40 -> 0.00743605 | I70: =H70 -> 0.00743605 | K70: =AVERAGE(E70:H70) -> 0.0063361867
A72: Share-based Compensation Expenses | E72: 292 | F72: 256 | G72: 237 | H72: 101 | I72: =I73*I17 -> 132.18635 | J72: =I72+H72 -> 233.18635 | K72: =$K$73*K17 -> 277.90909 | L72: =$K$73*L17 -> 289.20624 | M72: =$K$73*M17 -> 301.13316 | N72: =$K$73*N17 -> 313.72945
A73: %age of SG&A Expenses | E73: =E72/E17 -> 0.012050679 | F73: =F72/F17 -> 0.010345106 | G73: =G72/G17 -> 0.0089369886 | H73: =H72/H17 -> 0.0084040606 | I73: =H73 -> 0.0084040606 | J73: =J72/J17 -> 0.0084040606 | K73: =AVERAGE(E73:G73,J73) -> 0.0099342086
A74: Source | E74: 10K Dec'19, Pg 77 | H74: 10Q June'20, Pg 6
A76: Dividend Per Share | E76: 3.1675 | F76: 3.5875 | G76: 3.7925 | H76: 1.9775 | I76: =J76-H76 -> 1.648748 | J76: =$J$77*J50 -> 3.626248 | K76: =$J$77*K50 -> 3.7849863 | L76: =$J$77*L50 -> 3.9156616 | M76: =$J$77*M50 -> 4.0529304 | N76: =$J$77*N50 -> 4.1708685
A77: Dividend Payout Ratio | E77: =E76/E50 -> 0.60537812 | F77: =F76/F50 -> 0.63387322 | G77: =G76/G50 -> 0.68630836 | H77: N/A | J77: =AVERAGE(E77:G77) -> 0.64185323
A78: Source | E78: 10K Dec'19, Pg 39 | H78: 10Q June'20, Pg 9

Sheet Revenue Segments
A1: PepsiCo Inc. | J1: 6 month projection using 6 month growth rate from first halves of 19 and 20
A2: ='PepsiCo-IS'!A2 -> (in USD million except per Share Data) | M2: Year wise projection for 21 to 24 using yearly average growth rate from 16 to 19 (orange cell) | R2: This format has been used to project all other parameters as well
A3: Segment Information | B3: 12 | C3: ='PepsiCo-IS'!E3 -> 12 | D3: ='PepsiCo-IS'!F3 -> 12 | E3: ='PepsiCo-IS'!G3 -> 12 | G3: 6 | H3: ='PepsiCo-IS'!H3 -> 6 | J3: 6 | K3: ='PepsiCo-IS'!I3 -> 6 | M3: ='PepsiCo-IS'!J3 -> 12 | N3: ='PepsiCo-IS'!K3 -> 12 | O3: ='PepsiCo-IS'!L3 -> 12 | P3: ='PepsiCo-IS'!M3 -> 12 | Q3: ='PepsiCo-IS'!N3 -> 12
B4: 42735 | C4: ='PepsiCo-IS'!E4 -> 43100 | D4: ='PepsiCo-IS'!F4 -> 43465 | E4: ='PepsiCo-IS'!G4 -> 43830 | G4: 43646 | H4: ='PepsiCo-IS'!H4 -> 43995 | J4: 43830 | K4: ='PepsiCo-IS'!I4 -> 44196 | M4: ='PepsiCo-IS'!J4 -> 44196 | N4: ='PepsiCo-IS'!K4 -> 44561 | O4: ='PepsiCo-IS'!L4 -> 44926 | P4: ='PepsiCo-IS'!M4 -> 45291 | Q4: ='PepsiCo-IS'!N4 -> 45657
A5: FLNA | B5: 15549 | C5: 15798 | D5: 16346 | E5: 17078 | G5: 7825 | H5: 8347 | J5: =E5-G5 -> 9253 | K5: =J5*(1+K7) -> 9870.2608 | M5: =K5+H5 -> 18217.261 | N5: =M5*(1+$N7) -> 18882.006 | O5: =N5*(1+$N7) -> 19571.007 | P5: =O5*(1+$N7) -> 20285.15 | Q5: =P5*(1+$N7) -> 21025.352
A6: Growth% | C6: 0.02 | D6: =D5/C5-1 -> 0.034687935 | E6: =E5/D5-1 -> 0.044781598 | H6: =H5/G5-1 -> 0.066709265
A7: Organic Growth % | C7: 0.03 | D7: =D6 -> 0.034687935 | E7: =E6 -> 0.044781598 | F7: =AVERAGE(C7:E7) -> 0.036489844 | H7: =H6 -> 0.066709265 | K7: =H7 -> 0.066709265 | N7: =F7 -> 0.036489844
A8: Volume | C8: 0.01 | D8: 0.01 | E8: 0.02 | H8: 0.045
A9: Price | C9: =C7-C8 -> 0.02 | D9: =D7-D8 -> 0.024687935 | E9: =E7-E8 -> 0.024781598 | H9: =H7-H8 -> 0.021709265
A11: QFNA | B11: 2564 | C11: 2503 | D11: 2465 | E11: 2482 | G11: 1134 | H11: 1298 | J11: =E11-G11 -> 1348 | K11: =J11*(1+K13) -> 1542.9489 | M11: =K11+H11 -> 2840.9489 | N11: =M11*(1+$N13) -> 2823.6331 | O11: =N11*(1+$N13) -> 2806.4228 | P11: =O11*(1+$N13) -> 2789.3174 | Q11: =P11*(1+$N13) -> 2772.3163
A12: Growth% | C12: -0.02 | D12: =D11/C11-1 -> -0.015181782 | E12: =E11/D11-1 -> 0.0068965517 | H12: =H11/G11-1 -> 0.14462081
A13: Organic Growth % | C13: -0.01 | D13: =D12 -> -0.015181782 | E13: =E12 -> 0.0068965517 | F13: =AVERAGE(C13:E13) -> -0.0060950767 | H13: =H12 -> 0.14462081 | K13: =H13 -> 0.14462081 | N13: =F13 -> -0.0060950767
A14: Volume | C14: 0 | D14: -0.005 | E14: 0 | H14: 0.17
A15: Price | C15: =C13-C14 -> -0.01 | D15: =D13-D14 -> -0.010181782 | E15: =E13-E14 -> 0.0068965517 | H15: =H13-H14 -> -0.025379189
A17: PBNA | B17: 21312 | C17: 20936 | D17: 21072 | E17: 21730 | G17: 9832 | H17: 9808 | J17: =E17-G17 -> 11898 | K17: =J17*(1+K19) -> 11779.02 | M17: =K17+H17 -> 21587.02 | N17: =M17*(1+$N19) -> 21937.766 | O17: =N17*(1+$N19) -> 22294.21 | P17: =O17*(1+$N19) -> 22656.447 | Q17: =P17*(1+$N19) -> 23024.568
A18: Growth% | C18: =C17/B17-1 -> -0.017642643 | D18: =D17/C17-1 -> 0.0064959878 | E18: =E17/D17-1 -> 0.031226272 | H18: =H17/G17-1 -> -0.002441009
A19: Organic Growth % | D19: =D18 -> 0.0064959878 | E19: 0.026 | F19: =AVERAGE(C19:E19) -> 0.016247994 | H19: -0.01 | K19: =H19 -> -0.01 | N19: =F19 -> 0.016247994
A20: Volume | D20: -0.01 | E20: -0.01 | H20: -0.03
A21: Price | D21: =D19-D20 -> 0.016495988 | E21: =E19-E20 -> 0.036 | H21: 0.02
A23: LatAm | B23: 6820 | C23: 7208 | D23: 7354 | E23: 7573 | G23: 3127 | H23: 2877 | J23: =E23-G23 -> 4446 | K23: =J23*(1+K25) -> 4579.38 | M23: =K23+H23 -> 7456.38 | N23: =M23*(1+$N25) -> 8015.6085 | O23: =N23*(1+$N25) -> 8616.7791 | P23: =O23*(1+$N25) -> 9263.0376 | Q23: =P23*(1+$N25) -> 9957.7654
A24: Growth% | C24: =C23/B23-1 -> 0.056891496 | D24: =D23/C23-1 -> 0.020255272 | E24: =E23/D23-1 -> 0.029779712 | H24: =H23/G23-1 -> -0.079948833
A25: Organic Growth % | D25: 0.08 | E25: 0.07 | F25: =AVERAGE(C25:E25) -> 0.075 | H25: 0.03 | K25: =H25 -> 0.03 | N25: =F25 -> 0.075
A26: Volume | D26: 0.01 | E26: 0 | H26: 0.01
A27: Price | D27: =D25-D26 -> 0.07 | E27: =E25-E26 -> 0.07 | H27: 0.02
A29: Europe | C29: 10522 | D29: 10973 | E29: 11728 | G29: 4620 | H29: 4564 | J29: =E29-G29 -> 7108 | K29: =J29*(1+K31) -> 7321.24 | M29: =K29+H29 -> 11885.24 | N29: =M29*(1+$N31) -> 12628.067 | O29: =N29*(1+$N31) -> 13417.322 | P29: =O29*(1+$N31) -> 14255.904 | Q29: =P29*(1+$N31) -> 15146.898
A30: Growth% | D30: =D29/C29-1 -> 0.042862574 | E30: =E29/D29-1 -> 0.068805249 | H30: =H29/G29-1 -> -0.012121212
A31: Organic Growth % | D31: 0.07 | E31: 0.055 | F31: =AVERAGE(C31:E31) -> 0.0625 | H31: 0.03 | K31: =H31 -> 0.03 | N31: =F31 -> 0.0625
A32: Volume | D32: 0.05 | E32: -0.01 | H32: 0.03
A33: Price | D33: =D31-D32 -> 0.02 | E33: =E31-E32 -> 0.065 | H33: 0
A35: AMESA | C35: 3674 | D35: 3657 | E35: 3651 | G35: 1576 | H35: 1614 | J35: =E35-G35 -> 2075 | K35: =J35*(1+K37) -> 2095.75 | M35: =K35+H35 -> 3709.75 | N35: =M35*(1+$N37) -> 3913.7862 | O35: =N35*(1+$N37) -> 4129.0445 | P35: =O35*(1+$N37) -> 4356.1419 | Q35: =P35*(1+$N37) -> 4595.7297
A36: Growth% | D36: =D35/C35-1 -> -0.0046271094 | E36: =E35/D35-1 -> -0.0016406891 | H36: =H35/G35-1 -> 0.024111675
A37: Organic Growth % | D37: 0.05 | E37: 0.06 | F37: =AVERAGE(C37:E37) -> 0.055 | H37: 0.01 | K37: =H37 -> 0.01 | N37: =F37 -> 0.055
A38: Volume | D38: 0.015 | E38: 0.035 | H38: -0.01
A39: Price | D39: =D37-D38 -> 0.035 | E39: =E37-E38 -> 0.025 | H39: 0.02
A41: APAC | C41: 2884 | D41: 2794 | E41: 2919 | G41: 1219 | H41: 1318 | J41: =E41-G41 -> 1700 | K41: =J41*(1+K43) -> 1887 | M41: =K41+H41 -> 3205 | N41: =M41*(1+$N43) -> 3477.425 | O41: =N41*(1+$N43) -> 3773.0061 | P41: =O41*(1+$N43) -> 4093.7116 | Q41: =P41*(1+$N43) -> 4441.6771
A42: Growth% | D42: =D41/C41-1 -> -0.031206657 | E42: =E41/D41-1 -> 0.044738726 | H42: =H41/G41-1 -> 0.08121411
A43: Organic Growth % | D43: 0.08 | E43: 0.09 | F43: =AVERAGE(C43:E43) -> 0.085 | H43: 0.11 | K43: =H43 -> 0.11 | N43: =F43 -> 0.085
A44: Volume | D44: 0.06 | E44: 0.07 | H44: 0.07
A45: Price | D45: =D43-D44 -> 0.02 | E45: =E43-E44 -> 0.02 | H45: 0.05
A48: Total Division | B48: 62799 | C48: =C5+C11+C17+C23+C29+C35+C41 -> 63525 | D48: =D5+D11+D17+D23+D29+D35+D41 -> 64661 | E48: =E5+E11+E17+E23+E29+E35+E41 -> 67161 | G48: =G5+G11+G17+G23+G29+G35+G41 -> 29333 | H48: =H5+H11+H17+H23+H29+H35+H41 -> 29826 | J48: =J5+J11+J17+J23+J29+J35+J41 -> 37828 | K48: =K5+K11+K17+K23+K29+K35+K41 -> 39075.6 | M48: =SUM(M41,M35,M29,M23,M17,M11,M5) -> 68901.6 | N48: =SUM(N41,N35,N29,N23,N17,N11,N5) -> 71678.292 | O48: =SUM(O41,O35,O29,O23,O17,O11,O5) -> 74607.792 | P48: =SUM(P41,P35,P29,P23,P17,P11,P5) -> 77699.71 | Q48: =SUM(Q41,Q35,Q29,Q23,Q17,Q11,Q5) -> 80964.308
C49: =C48/B48-1 -> 0.011560694 | D49: =D48/C48-1 -> 0.017882723 | E49: =E48/D48-1 -> 0.038663182 | H49: =H48/G48-1 -> 0.016807009
A51: Source | B51: 10K Dec'16, Pg 4 | C51: 10K Dec'19, Pg 84 and 51, 10K Dec'18, Pg 60 | G51: 10Q June'20, Pg 11 and 35 | J51: Calculation | M51: Calculation
